[
  {
    "content": "",
    "name": "李芳",
    "setTime": "1 週前",
    "star": 5
  },
  {
    "content": "免費的景觀，一定要來走走看看。",
    "name": "Vaster (光點嚮導•等級12)",
    "setTime": "2 週前",
    "star": 5
  },
  {
    "content": "",
    "name": "Ryan",
    "setTime": "1 個月前",
    "star": 5
  },
  {
    "content": "1，天然美景鬼斧神工就是好看\n2，美中不足垃圾偏多，海蟑螂四竄\n3，沒有安全防護措施，遊客要自己多加留意",
    "name": "Jack Wu",
    "setTime": "2 個月前",
    "star": 3
  },
  {
    "content": "",
    "name": "張靜雯",
    "setTime": "2 個月前",
    "star": 1
  },
  {
    "content": "海岸垃圾破壞了美景。",
    "name": "andrew chuang",
    "setTime": "2 個月前",
    "star": 5
  },
  {
    "content": "景色宜人 歡喜的海邊",
    "name": "簡連鴻",
    "setTime": "3 個月前",
    "star": 5
  },
  {
    "content": "岩石上一片海水灘，很靜！\n倒出小吳哥窟的樣子！",
    "name": "Andy Chen",
    "setTime": "3 個月前",
    "star": 5
  },
  {
    "content": "",
    "name": "劉秀蘭",
    "setTime": "3 個月前",
    "star": 5
  },
  {
    "content": "",
    "name": "張文祥",
    "setTime": "3 個月前",
    "star": 4
  },
  {
    "content": "",
    "name": "Chen Kimbal",
    "setTime": "4 個月前",
    "star": 4
  },
  {
    "content": "很漂亮的海岸，特殊的石頭，但就是太少了",
    "name": "曾寶寶寶",
    "setTime": "4 個月前",
    "star": 3
  },
  {
    "content": "",
    "name": "阮如軒",
    "setTime": "4 個月前",
    "star": 5
  },
  {
    "content": "",
    "name": "Tony Huang",
    "setTime": "4 個月前",
    "star": 4
  },
  {
    "content": "很漂亮 記得防曬",
    "name": "潘餅",
    "setTime": "5 個月前",
    "star": 4
  },
  {
    "content": "",
    "name": "丫泰",
    "setTime": "5 個月前",
    "star": 5
  },
  {
    "content": "很特殊的一個海岸景觀，整一大片長滿海草的岩石。\n還可以在上面行走，不過還是要小心以免滑倒。",
    "name": "CHI MING CHEN",
    "setTime": "6 個月前",
    "star": 5
  },
  {
    "content": "停留20分鐘左右，對面也有停車位",
    "name": "葵鹿金",
    "setTime": "7 個月前",
    "star": 4
  },
  {
    "content": "",
    "name": "高小樹",
    "setTime": "7 個月前",
    "star": 4
  },
  {
    "content": "",
    "name": "孟聖力",
    "setTime": "7 個月前",
    "star": 3
  },
  {
    "content": "南雅奇石地質步道的入口就位於南雅漁港停車場的涼亭旁邊，從這裡可以一路走到南雅奇石，中途會經過南雅觀景台，沿途奇岩怪石嶙峋，令人讚歎不已，唯一不美之處，就是沿岸海洋垃圾也不少，影響了景區觀瞻。\n抵達南雅奇石時，整個景觀更加可觀，由於地質岩層長時間的經受東北季風與海洋強浪侵蝕作用，因此形成各種千奇百怪的奇石巨岩景觀，其中類似彩繪的獨特紋路更是此地最特別的景色，除了有霜淇淋岩、竹筍岩與著名的海狗岩等等，還可以觀覽海天一色的美景；也可在稍遠處欣賞一座座鬼斧神工的奇岩羅列交錯，加堪稱世界級奇景。",
    "name": "陳炎能",
    "setTime": "8 個月前",
    "star": 5
  },
  {
    "content": "",
    "name": "廖Emily",
    "setTime": "8 個月前",
    "star": 4
  },
  {
    "content": "是個風景很漂亮的地方，要拍美照，那就要上下找尋拍照的最佳地點，我覺得角度抓對了每一張也漂亮。",
    "name": "張惠菱",
    "setTime": "8 個月前",
    "star": 5
  },
  {
    "content": "",
    "name": "江麗娟",
    "setTime": "9 個月前",
    "star": 5
  },
  {
    "content": "廟的對面有停車場\n可步行到漁港跟南雅奇石地質步道",
    "name": "Vincent Hsu",
    "setTime": "10 個月前",
    "star": 4
  },
  {
    "content": "對面有很大的停車場 非常方便",
    "name": "ling H.",
    "setTime": "11 個月前",
    "star": 5
  },
  {
    "content": "",
    "name": "Jamilah Mila",
    "setTime": "11 個月前",
    "star": 5
  },
  {
    "content": "太開心看到那麽美的地形\n北海岸沿路都超美的\n海水好藍\n雲好白\n\n只有可惜垃圾多\n下次去想去撿",
    "name": "一起玩生活",
    "setTime": "11 個月前",
    "star": 5
  },
  {
    "content": "",
    "name": "先生小姐",
    "setTime": "11 個月前",
    "star": 5
  },
  {
    "content": "",
    "name": "許倍瑟",
    "setTime": "11 個月前",
    "star": 5
  },
  {
    "content": "",
    "name": "朱沛育",
    "setTime": "11 個月前",
    "star": 3
  },
  {
    "content": "不亞於野柳地質奇石，範圍雖不大在東北角旅遊或健行完南子杏步道後可順路來此一遊。",
    "name": "richard Chou",
    "setTime": "1 年前",
    "star": 4
  },
  {
    "content": "沿路很多垃圾",
    "name": "Charming Chang",
    "setTime": "1 年前",
    "star": 4
  },
  {
    "content": "很適合全家出遊的地方，這裡看一看的螃蟹🦀️、魚🐟，還有很像狗、筍子、章魚🐙的岩石哦～有美麗海景，退潮時可以泡泡海水還蠻不錯的。在馬路對岸有小小的免費停車場。\n還有很多人在這裡拍婚紗，相信大家可以在這裡拍出很多美美的照片喔～ …",
    "name": "Stacy 惠惠",
    "setTime": "1 年前",
    "star": 5
  },
  {
    "content": "短短的、沿途石頭很美",
    "name": "Hsin",
    "setTime": "1 年前",
    "star": 5
  },
  {
    "content": "岩體有發達的垂直節理，在海浪衝擊侵蝕下，形成各種特殊地形如：海蝕崖、海溝、造形石等。其中又以岩塊中層理交疊，地下水帶來氧化鐵沿節理浸染形成風化痕，岩塊裂解形成柱狀神似一枝霜淇淋，是本地最具代表的景觀。風化紋常是雕塑海岸岩石的主手。此外還有風化地形的風化窗、蕈狀岩、岩峰、蜂窩岩，還有海蝕地形中的海蝕崖、海蝕凹壁、海蝕平台等地形景觀，還有長期受海水漩渦式迴轉侵蝕所刻畫出來的地質小景觀壺穴等，哇...啊！這真是大自然的鬼斧神工，確實令人驚豔！是一處適合親子共同遊賞及學習的優質步道。",
    "name": "liest wang",
    "setTime": "1 年前",
    "star": 5
  },
  {
    "content": "時間:2022年7月9日\n縣市:新北市瑞芳區\n地點:南雅奇石\n天氣:晴\n說明:位於新北市瑞芳區的南雅海邊，沿途可見奇石嶙峋、山海相映的壯闊美景，此處遮蔽較少，僅有數處涼亭可供休息，商家基本集中在南雅南福宮周邊，有小吃店、冰店、柑仔店，數量不多，小吃以海鮮類為主。\n建議前來遊玩的旅客要做好充分防曬，並攜帶足夠水量，我是約莫中午前來，風景非常漂亮，只是在太陽底行走下，沒有下去玩水的話，真的很容易發生中暑的狀況。\n比較適合清晨天剛破曉，或是傍晚時分前來，斜射光讓奇石更顯美麗，這裡也是拍攝日出的好地方。",
    "name": "秋月風華",
    "setTime": "1 年前",
    "star": 5
  },
  {
    "content": "",
    "name": "施志興",
    "setTime": "1 年前",
    "star": 5
  },
  {
    "content": "很美，但是不建議假日來，車太多了，沿著步道走還不錯，輕鬆，時間多可以上南子杏步道上登高望遠，又是新的風景。",
    "name": "Justin Liu",
    "setTime": "1 年前",
    "star": 5
  },
  {
    "content": "微風吹拂，晚霞映照，走在步道上，看著奇岩雅石，海浪拍打著礁石上，快意不過了。",
    "name": "ken chen",
    "setTime": "1 年前",
    "star": 4
  },
  {
    "content": "",
    "name": "黃治誠",
    "setTime": "1 年前",
    "star": 4
  },
  {
    "content": "",
    "name": "yiwen hsu",
    "setTime": "1 年前",
    "star": 4
  },
  {
    "content": "",
    "name": "洪旺才",
    "setTime": "1 年前",
    "star": 4
  },
  {
    "content": "每次經過很多人，而且蠻多三寶過馬路都不看車的！",
    "name": "戴家寶",
    "setTime": "1 年前",
    "star": 4
  },
  {
    "content": "海岸邊 風景秀麗\n就是有些漂浮垃圾",
    "name": "Li richard",
    "setTime": "1 年前",
    "star": 4
  },
  {
    "content": "很特別的自然景觀",
    "name": "Ku Lin",
    "setTime": "1 年前",
    "star": 5
  },
  {
    "content": "好的",
    "name": "Daniel SUNG",
    "setTime": "1 年前",
    "star": 3
  },
  {
    "content": "停車即可欣賞美景",
    "name": "張明泉",
    "setTime": "1 年前",
    "star": 5
  },
  {
    "content": "步道修整後好走好觀賞海景，適合帶長者親子遊玩散步的步道(但靠海岸行走，小孩要注意)",
    "name": "Meg Hsu",
    "setTime": "1 年前",
    "star": 5
  },
  {
    "content": "非常推薦的步道，沿途有許多打卡拍照點，天氣好時更是美麗。",
    "name": "黃偉峰",
    "setTime": "1 年前",
    "star": 5
  },
  {
    "content": "很有特色的地質景觀，像星際科幻片的布景。",
    "name": "Jeng-Tsai Lee",
    "setTime": "1 年前",
    "star": 4
  },
  {
    "content": "有種野柳風景區的既視感\n很適合拍網美照",
    "name": "林慈軒",
    "setTime": "1 年前",
    "star": 4
  },
  {
    "content": "",
    "name": "Wei Shan",
    "setTime": "1 年前",
    "star": 5
  },
  {
    "content": "來這裡看海看大自然地理景觀的好地方，停車可以停在南雅漁港免費停車場旁，步道走過來，七分鐘可到，步道上海蟑螂超多，林投樹會勾人需留意，但還是非常推薦這裡，不用走很遠就會看到大自然美景盡收眼底，陽光☀️照下來像黃金般的美景，真的好喜歡！對面街口的南新宮廟宇有提供算乾淨的洗手間",
    "name": "melody melody",
    "setTime": "1 年前",
    "star": 5
  },
  {
    "content": "適合開車累了 停下來休息走走",
    "name": "Ying-Hao Chu",
    "setTime": "1 年前",
    "star": 4
  },
  {
    "content": "規劃完整",
    "name": "TING LIN",
    "setTime": "2 年前",
    "star": 5
  },
  {
    "content": "北海岸的海蝕地形，美麗驚奇",
    "name": "鍾松財z19651016",
    "setTime": "2 年前",
    "star": 4
  },
  {
    "content": "",
    "name": "邱仔",
    "setTime": "2 年前",
    "star": 5
  },
  {
    "content": "坐公車來到南雅奇石  一定是從南新宮站牌下車\n下車後不一定要沿著馬路走過\n可以從海側的 『南雅奇石地質步道』走過去\n從地質步道走過去 會有不同的景色\n退潮時可以向海岸走去  整片的海蝕平台景色也很棒\n有時還能看到各種海洋生物",
    "name": "酷猫猫",
    "setTime": "2 年前",
    "star": 5
  },
  {
    "content": "在公路旁平行的一小段步道，充滿奇異的地質景觀，看得見海看得見岩石看得見垃圾.....",
    "name": "L",
    "setTime": "2 年前",
    "star": 5
  },
  {
    "content": "",
    "name": "陳世泓",
    "setTime": "2 年前",
    "star": 5
  },
  {
    "content": "開車進入瑞芳 南雅奇石地質景觀步道 哇滿片岩石是非常的漂亮 把車停好然後下海邊岩石 年輕的走路就很順年紀大的 要 牽著手 扶著上下 岩石 免得跌倒  南雅奇石 也經常有電視台有拍廣告影片 是非常的漂亮數一數二的景點 有的景點海溝是很深很危險 遊客進入大家都要步步小心免得發生意外",
    "name": "范上林",
    "setTime": "2 年前",
    "star": 4
  },
  {
    "content": "",
    "name": "Sam Hsieh",
    "setTime": "2 年前",
    "star": 5
  },
  {
    "content": "好的",
    "name": "Shu-Ming Tseng",
    "setTime": "2 年前",
    "star": 5
  },
  {
    "content": "南雅奇石被海蝕，\n行成獨特的筍石；\n還有霜淇淋岩石，\n看了口水直直流；\n海蝕崖觸目驚心，\n告訴遊客要小心；\n珍惜當前的美景，\n請勿攀爬傷岩心；\n保護奇石的外型，\n留給後代的子孫！",
    "name": "曾銘輝",
    "setTime": "2 年前",
    "star": 4
  },
  {
    "content": "",
    "name": "呂芳良",
    "setTime": "2 年前",
    "star": 5
  },
  {
    "content": "南雅奇石果然名不虛傳，值得一探，可惜環境維護待加強",
    "name": "靖菱瑛",
    "setTime": "2 年前",
    "star": 4
  },
  {
    "content": "海邊空氣很好，步道很好走，看海聽濤，加上一些崎岩怪石值得大家來觀賞！",
    "name": "楊濟強",
    "setTime": "2 年前",
    "star": 4
  },
  {
    "content": "沈積岩風化而成的景點 特別吸睛 唯現場安全維護 仍有改善空間。",
    "name": "郭冠均",
    "setTime": "2 年前",
    "star": 4
  },
  {
    "content": "",
    "name": "Lily",
    "setTime": "2 年前",
    "star": 5
  }
]