[
  {
    "content": "只適合拍照 其餘沒有農場的感覺😥 …",
    "name": "YYin Xin",
    "setTime": "15 小時前",
    "star": 2
  },
  {
    "content": "環境乾淨漂亮產品品質很好\n彰化的朋友進場免費",
    "name": "黃明毅",
    "setTime": "2 天前",
    "star": 5
  },
  {
    "content": "風景優美氣氛佳……散步賞景超優質喔！情侶約會－帶長輩小孩最適合喔！",
    "name": "陳冷兒",
    "setTime": "2 天前",
    "star": 5
  },
  {
    "content": "無論四面八..無論上下左右都美極了..美呆了...真是夢幻仙境喔！..",
    "name": "陳大B",
    "setTime": "2 天前",
    "star": 5
  },
  {
    "content": "悠閒好地方 可以來曬小孩 彰化人有優待喔 👍",
    "name": "張佑甄",
    "setTime": "2 天前",
    "star": 4
  },
  {
    "content": "很好逛👍好多東西可買，有餐點可使用，活動空間很大！",
    "name": "張瑞華",
    "setTime": "2 天前",
    "star": 5
  },
  {
    "content": "這裡適合拍照，在地美食也很多,我非常喜歡這裡。",
    "name": "游婷雁",
    "setTime": "2 天前",
    "star": 5
  },
  {
    "content": "服務好、好拍照、適合情侶或一家大小來走走，超讚der 😄 …",
    "name": "羅秀文",
    "setTime": "2 天前",
    "star": 5
  },
  {
    "content": "第一次來，感覺很棒，很新鮮，下次再帶孩子過來！",
    "name": "顏介齡",
    "setTime": "2 天前",
    "star": 5
  },
  {
    "content": "",
    "name": "吳怡芳",
    "setTime": "2 天前",
    "star": 5
  },
  {
    "content": "第一次來琉璃仙境休閒農場可以進来看看1",
    "name": "張達瑋",
    "setTime": "2 天前",
    "star": 5
  },
  {
    "content": "來當一日網紅拍美美照！怎麼拍怎麼美！",
    "name": "蘇均霈",
    "setTime": "2 天前",
    "star": 5
  },
  {
    "content": "空間很大，有提供傘遮陽，蠻好拍的，憑入園票根三個月內可以再來一次。",
    "name": "葉家莉",
    "setTime": "2 天前",
    "star": 5
  },
  {
    "content": "",
    "name": "吳宗哲",
    "setTime": "2 天前",
    "star": 4
  },
  {
    "content": "場內感覺凌亂",
    "name": "廖敏男",
    "setTime": "3 天前",
    "star": 3
  },
  {
    "content": "小孩喜歡玩大草地玩大球，風景美氣氛佳！遛小孩好地方！",
    "name": "高鈞蓉（Joyce）",
    "setTime": "3 天前",
    "star": 5
  },
  {
    "content": "風景美.氣氛佳讓人很放鬆\n很適合拍照，怎麼拍 都好拍.",
    "name": "陳駿瑋",
    "setTime": "3 天前",
    "star": 5
  },
  {
    "content": "網美拍照景點，喜歡拍照的只要選個大晴天，怎麼拍都好看，彰化地區遛小孩的好地方",
    "name": "Asdf Qwer",
    "setTime": "3 天前",
    "star": 5
  },
  {
    "content": "很開心這次來到琉璃仙境，是個拍婚紗的聖地，景點優美！！",
    "name": "陳宜靜",
    "setTime": "3 天前",
    "star": 5
  },
  {
    "content": "哇！真是人間仙境的一處好景點\n錯過妳或你就會後悔喔！",
    "name": "林彥誼",
    "setTime": "3 天前",
    "star": 5
  },
  {
    "content": "第一次來這裡\n園區很大，建築物很美，很適合拍照也很適合帶小朋友來",
    "name": "ann c",
    "setTime": "3 天前",
    "star": 5
  },
  {
    "content": "3D壁畫很讚，非常適合拍照，而且有很多可愛的建築。",
    "name": "陳意涵",
    "setTime": "3 天前",
    "star": 5
  },
  {
    "content": "樂樂導覽員非常可愛又優秀，聲音甜美又迷人，琉璃仙境真夢幻！",
    "name": "呆呆黃",
    "setTime": "3 天前",
    "star": 5
  },
  {
    "content": "非常漂亮的，解說員超級棒，我們非常喜歡，會再帶其他親朋好友好玩",
    "name": "王麗凰",
    "setTime": "3 天前",
    "star": 5
  },
  {
    "content": "紀念品精緻，還有熊貓表演，適合全家大小一起來的地方，停車位也好找",
    "name": "謝佳峰",
    "setTime": "3 天前",
    "star": 5
  },
  {
    "content": "免費停車，購物可刷卡，可用載具，店員態度很好，廁所乾淨",
    "name": "吳旌綾（Elaine）",
    "setTime": "3 天前",
    "star": 5
  },
  {
    "content": "環境優美適合放鬆的地方，吃火鍋的地方很像膠囊旅店，很新奇",
    "name": "鄒明學",
    "setTime": "3 天前",
    "star": 5
  },
  {
    "content": "有如置身在國外的環境！",
    "name": "高福順",
    "setTime": "3 天前",
    "star": 4
  },
  {
    "content": "這邊的風景很漂亮肥皂很好用有香香的味道還可以試用",
    "name": "謝佳吟",
    "setTime": "3 天前",
    "star": 5
  },
  {
    "content": "這裡園區很漂亮很適合來這拍照或是你們可以來這裡吃飯",
    "name": "白美鳳",
    "setTime": "3 天前",
    "star": 5
  },
  {
    "content": "帶小孩全家人來拍照的好地方  停車方便  適合全家老少出遊的好地方",
    "name": "范小玉",
    "setTime": "3 天前",
    "star": 5
  },
  {
    "content": "非常好逛的地方 有如仙境一般。可以帶全家出遊的好地方",
    "name": "高端疫苗",
    "setTime": "3 天前",
    "star": 5
  },
  {
    "content": "園區大大大，\n左手香涼膏讚，\n晨曦之露香香….\n\n戶外有小黑蚊，擦涼膏真的好😊",
    "name": "洪茹茵",
    "setTime": "3 天前",
    "star": 5
  },
  {
    "content": "非常優質的景點 餐點好吃 很適合拍網紅照的好地方",
    "name": "陳宏彬",
    "setTime": "3 天前",
    "star": 5
  },
  {
    "content": "來到琉璃仙境來了還會想再來好拍好美好買午餐的餐廳好吃又舒服好去處",
    "name": "蘇蕉如",
    "setTime": "3 天前",
    "star": 5
  },
  {
    "content": "超讚真的好玩，來很多次都不會厭倦，網美拍照揪好朋友來玩，午餐也超讚👍👍👍",
    "name": "許淑梅",
    "setTime": "3 天前",
    "star": 5
  },
  {
    "content": "超讚的",
    "name": "Thuymui Ta",
    "setTime": "3 天前",
    "star": 5
  },
  {
    "content": "風景漂亮，是拍網美照的好地方，下次還要揪朋友一起來。",
    "name": "陳琴",
    "setTime": "3 天前",
    "star": 5
  },
  {
    "content": "",
    "name": "江姿瑩",
    "setTime": "3 天前",
    "star": 5
  },
  {
    "content": "門票200元連杯飲料也沒有，只能換$50魚飼料，",
    "name": "黃昭元",
    "setTime": "3 天前",
    "star": 1
  },
  {
    "content": "",
    "name": "李小樺",
    "setTime": "4 天前",
    "star": 4
  },
  {
    "content": "必須說，景點挺普通的，不過彰化縣民可以免費入場，閒晃 聊聊天、吃個下午茶是也還行",
    "name": "陳銘仕（木瓜王）",
    "setTime": "4 天前",
    "star": 4
  },
  {
    "content": "餐點好吃不貴，園區漂亮好看又好拍，香氛吊飾不錯，服務人員超親切，可以再來玩",
    "name": "許俊維",
    "setTime": "4 天前",
    "star": 5
  },
  {
    "content": "現場好拍好逛 手工皂那邊種類很多也很香 戶外的冰也是很好吃\n還提供免費陽傘供遊客使用 很讚 很適合帶小孩來走走",
    "name": "想安靜",
    "setTime": "4 天前",
    "star": 5
  },
  {
    "content": "這裡超讚，服務人員親切、香皂超讚👍，有機會還要再來 …",
    "name": "Jacky",
    "setTime": "4 天前",
    "star": 5
  },
  {
    "content": "",
    "name": "林育詮",
    "setTime": "5 天前",
    "star": 5
  },
  {
    "content": "",
    "name": "謝豐濂",
    "setTime": "5 天前",
    "star": 5
  },
  {
    "content": "環境很乾淨很涼很舒服 走到哪香到哪 店員態度也好",
    "name": "陳冠丞",
    "setTime": "6 天前",
    "star": 5
  },
  {
    "content": "拍照好去處買票員工講解很詳盡\n下次還能免費入園",
    "name": "盧湘玉",
    "setTime": "6 天前",
    "star": 5
  },
  {
    "content": "服務態度好 紀念品店裡面超級涼 也很好拍照",
    "name": "楊再欣",
    "setTime": "6 天前",
    "star": 5
  },
  {
    "content": "環境很涼很乾淨 店員態度極佳 很香 護手霜很香",
    "name": "李雅婷",
    "setTime": "6 天前",
    "star": 5
  },
  {
    "content": "紀念品店裡很涼很舒服很乾淨 店員很可愛 東西超級香",
    "name": "李家家",
    "setTime": "6 天前",
    "star": 5
  },
  {
    "content": "粉色白色教堂漂亮，環境優美，景色漂亮，好拍，舒適的休閒娛樂。",
    "name": "張素玲",
    "setTime": "6 天前",
    "star": 5
  },
  {
    "content": "裡面很有二家開放散客的用餐空間，都有賣火鍋。\n另一家在粉紅色的餐廳是開放預訂的團客用。\n打卡是好拍，但建議行程規畫要另找其他地點搭配遊玩。",
    "name": "Craig YANG",
    "setTime": "6 天前",
    "star": 3
  },
  {
    "content": "",
    "name": "貴貴",
    "setTime": "6 天前",
    "star": 5
  },
  {
    "content": "園區很好逛 服務員樂樂服務很好很棒又長得漂亮🫶🏻 …",
    "name": "賴軒羽",
    "setTime": "6 天前",
    "star": 5
  },
  {
    "content": "網美拍照景點，喜歡拍照的只要選個大晴天，怎麼拍都好看，園區小，門票貴，CP值不高。",
    "name": "JIA-HUI ZHAN",
    "setTime": "1 週前",
    "star": 3
  },
  {
    "content": "很好拍照的地方，餐點有待加強",
    "name": "林佳佳",
    "setTime": "1 週前",
    "star": 3
  },
  {
    "content": "服務人員\n親切又有禮貌\n園區繽紛美麗👍👍👍 …",
    "name": "陳Apple",
    "setTime": "1 週前",
    "star": 5
  },
  {
    "content": "店家服務人員非常親切的解說，環境很舒服非常值得來逛逛，拍照打卡聖地讚👍👍👍",
    "name": "神秘人",
    "setTime": "1 週前",
    "star": 5
  },
  {
    "content": "場景不錯，部分門票費用可以折抵商品，景色好拍，有小動物可以看，場地還算大",
    "name": "戀小紫",
    "setTime": "1 週前",
    "star": 5
  },
  {
    "content": "今日來訪第一次。覺得很漂亮。好拍照。也有提供雨傘遮陽。貼心的服務。",
    "name": "趙小沛",
    "setTime": "1 週前",
    "star": 5
  },
  {
    "content": "環境很漂亮 整理的非常用心！ 服務生的態度都很好唷～ 園區裡個個都是驚喜的小角落 值得來拍美照喔！👍 …",
    "name": "張育謙",
    "setTime": "1 週前",
    "star": 5
  },
  {
    "content": "停車方便，園區空間大造景用心打理，餐食多選擇，適合全家走走。",
    "name": "許品嫺",
    "setTime": "1 週前",
    "star": 5
  },
  {
    "content": "",
    "name": "Maggie Shen",
    "setTime": "1 週前",
    "star": 5
  },
  {
    "content": "彰化縣民免費入園活動到月底，剛好順便來買個去角質霜、吃個小火鍋哦",
    "name": "廖櫻桃",
    "setTime": "1 週前",
    "star": 5
  },
  {
    "content": "",
    "name": "林鈺凱",
    "setTime": "1 週前",
    "star": 5
  },
  {
    "content": "",
    "name": "素蘭鄭",
    "setTime": "1 週前",
    "star": 3
  },
  {
    "content": "",
    "name": "沅和李",
    "setTime": "1 週前",
    "star": 4
  },
  {
    "content": "這裡很適合情侶來這裡玩 拍照和打卡都很適合，這裡還很貼心有雨傘可以借",
    "name": "霹靂天神",
    "setTime": "1 週前",
    "star": 5
  },
  {
    "content": "今天太陽很熱，環境還OK，冷氣很舒服,值得來看看的地方",
    "name": "geta Pee",
    "setTime": "1 週前",
    "star": 5
  },
  {
    "content": "這邊的食物很好吃，然後環境也很漂亮，非常推",
    "name": "李瑞玉",
    "setTime": "1 週前",
    "star": 5
  },
  {
    "content": "",
    "name": "彭淑玲",
    "setTime": "1 週前",
    "star": 4
  },
  {
    "content": "餐點，湯頭都不錯，肉粉嫩好吃也很好拍照的地方，唯一缺點停車場有點小，不好停車",
    "name": "SM SUMMON",
    "setTime": "1 週前",
    "star": 5
  },
  {
    "content": "這裡很好拍照，咖哩火鍋好吃，服務親切，廁所有冷氣，也可放風小孩，值得一遊。",
    "name": "Apple Juice",
    "setTime": "1 週前",
    "star": 5
  },
  {
    "content": "園區超美，適合遛小孩跟拍美照，\n園區也有販售部，裡面超香環境不錯，\n值得情侶來拍照",
    "name": "賴小婷",
    "setTime": "1 週前",
    "star": 5
  },
  {
    "content": "琉璃仙境彰化線民免費入場到8/31，親子放電好去處，寵物友善空間，好拍攝。",
    "name": "思萱李",
    "setTime": "1 週前",
    "star": 5
  },
  {
    "content": "趁免費入園，可以帶小朋友來玩大球，還能吃火鍋，看熊貓跳舞。",
    "name": "bally",
    "setTime": "1 週前",
    "star": 5
  },
  {
    "content": "琉璃仙境休閒農場假日的時候很適合全家大小來走走的地方很適合來溜小孩",
    "name": "何建樺",
    "setTime": "1 週前",
    "star": 5
  },
  {
    "content": "琉璃仙境休閒農場很适合全家大小游玩，超級棒的！",
    "name": "叶爱芳",
    "setTime": "1 週前",
    "star": 5
  },
  {
    "content": "拍起照很美，火鍋也蠻不錯吃，有機會再來一遊",
    "name": "俐雯錢",
    "setTime": "1 週前",
    "star": 5
  },
  {
    "content": "出遊好去處~餐點多元好吃，風景優美，還有表演欣賞，推薦！",
    "name": "小小儀（Evonne）",
    "setTime": "1 週前",
    "star": 5
  },
  {
    "content": "彰化員林好去處\n適合一家大小來拍照留念",
    "name": "彭立琪",
    "setTime": "1 週前",
    "star": 5
  },
  {
    "content": "全家出遊好去處，風景優美，餐點好吃~",
    "name": "Patty Ho",
    "setTime": "1 週前",
    "star": 5
  },
  {
    "content": "放假休閒好逛，可以帶小朋友放風，大人也可以休息的好地方",
    "name": "戴保漢",
    "setTime": "1 週前",
    "star": 5
  },
  {
    "content": "五星評論送紀念品\n裡面可以拍拍美照\n門票三個月內來可以免費入場（帶門票）",
    "name": "陳宥慈",
    "setTime": "1 週前",
    "star": 5
  },
  {
    "content": "色彩鮮豔的教堂宛如仙境，身心愉悅的一日遊及親切的服務人員",
    "name": "c sa",
    "setTime": "1 週前",
    "star": 5
  },
  {
    "content": "風景美好拍照的地方，適合親子來遊玩，很棒的地方",
    "name": "陳雲卿",
    "setTime": "1 週前",
    "star": 5
  },
  {
    "content": "親子約會的好地方.適合戶外踏青的好地方.",
    "name": "加國尤",
    "setTime": "1 週前",
    "star": 5
  },
  {
    "content": "很棒，很漂亮風景非常的讚， 熊貓跳舞跳得很棒很可愛， 涼風徐徐吹來陶醉了。",
    "name": "陳俊全666",
    "setTime": "1 週前",
    "star": 5
  },
  {
    "content": "很漂亮 唱歌很好聽 熊貓很可愛很會跳舞 大小朋友都開心",
    "name": "Katherine Chen",
    "setTime": "1 週前",
    "star": 5
  },
  {
    "content": "琉璃仙境休閒農場～好玩～很漂亮～熊貓表演很逗趣 適合大小朋友同樂😆🐼 …",
    "name": "Yao A",
    "setTime": "1 週前",
    "star": 5
  },
  {
    "content": "環境美，地方佳；適合戶外踏青、約會的地方，也適合親子遊樂的地方",
    "name": "牛軋糖",
    "setTime": "1 週前",
    "star": 5
  },
  {
    "content": "很棒的休閒環境，很多很好拍的網美點！",
    "name": "jill Chen",
    "setTime": "1 週前",
    "star": 5
  },
  {
    "content": "店員服務很親切  環境清幽適合遛狗遛小孩的好地方 也有店家可以逛～",
    "name": "陳梓妍",
    "setTime": "1 週前",
    "star": 5
  },
  {
    "content": "暑假出遊⋯拍照逛逛非常適合。\n入園門票200/人，可折抵消費",
    "name": "Ruby Guo",
    "setTime": "1 週前",
    "star": 5
  },
  {
    "content": "環境優美 很多景可以拍照 也適合全家大小來",
    "name": "Sunny RED FINGER",
    "setTime": "1 週前",
    "star": 5
  },
  {
    "content": "彰化縣民優惠免門票，小巧的園區平日人潮不多可悠閒逛逛！",
    "name": "陳天敏",
    "setTime": "1 週前",
    "star": 5
  },
  {
    "content": "停車方便且園區內很多景點可以拍照，門票也有折抵餐點跟購物。",
    "name": "Dylan Gino",
    "setTime": "1 週前",
    "star": 5
  },
  {
    "content": "好拍好買手工皂好吃的網美拍照景點，適合喜歡拍照的網美＾＾",
    "name": "許博凱",
    "setTime": "1 週前",
    "star": 5
  },
  {
    "content": "適合親子旅遊，非常好拍，而且三個月內還可以評卷在來一次免費入園，超棒的！",
    "name": "黃小皮",
    "setTime": "1 週前",
    "star": 5
  },
  {
    "content": "今天有藍天白雲，可以拍到美美的照片，心情非常開心。",
    "name": "陳文彬",
    "setTime": "1 週前",
    "star": 5
  },
  {
    "content": "好適合親子遊唷\n吃吃雪花冰\n拍拍各地美照\n渡過炎熱的夏天",
    "name": "林慧卿",
    "setTime": "1 週前",
    "star": 5
  },
  {
    "content": "風景優美，拍照的好地方，服務人員親切，餐點好吃環境乾淨。",
    "name": "Stanley Chang",
    "setTime": "1 週前",
    "star": 5
  },
  {
    "content": "",
    "name": "靜靜",
    "setTime": "1 週前",
    "star": 4
  },
  {
    "content": "東西不錯吃 推薦麻辣湯頭小火鍋\n裡面設施乾淨 好拍👍",
    "name": "婷婷",
    "setTime": "1 週前",
    "star": 5
  },
  {
    "content": "",
    "name": "江秀美",
    "setTime": "1 週前",
    "star": 4
  },
  {
    "content": "",
    "name": "張真真",
    "setTime": "1 週前",
    "star": 4
  },
  {
    "content": "",
    "name": "品馨曾",
    "setTime": "2 週前",
    "star": 4
  },
  {
    "content": "這裡好美，東西好聞好買，食物好吃，店員服務親切~",
    "name": "歆喬",
    "setTime": "2 週前",
    "star": 5
  },
  {
    "content": "有停車場🅿️ 不用擔心沒地方停\n門票一個人$200\n有附贈餐廳85折券+一些商店折抵券\n裡面非常好拍照 有很多景可以拍\n屬於親子、情人、老人踏青都適合的地方",
    "name": "黃晶湄",
    "setTime": "2 週前",
    "star": 5
  },
  {
    "content": "拍照的好景點,但格局不大,環境稍嫌擁擠,門票抵消費的規定欠缺誠意.",
    "name": "黃志成",
    "setTime": "2 週前",
    "star": 4
  },
  {
    "content": "看到網路照片很美，所以來參觀。\n門票一張250，內部大約20～30分鐘逛完。覺得CP值不高。\n而且門票折抵部份只能一筆購物消費,折抵一張50元，然後餐飲不包括在內（餐飲憑票根85折，根本多此一舉，難道有人沒購票就能進來吃東西嗎？）……\n那麼這樣就感覺門票費用不值得了……",
    "name": "MIKI",
    "setTime": "2 週前",
    "star": 2
  },
  {
    "content": "",
    "name": "HU辣椒",
    "setTime": "2 週前",
    "star": 5
  },
  {
    "content": "火鍋吃到飽，補料補很慢，而且補的份量跟來客數明顯差別很大，導覽員說好用餐時間幾分鐘，結果呢？還沒到用餐時間，我們尚未吃飽就叫全部客人到外面，因為他要推銷景區商品跟擂茶 真的絕不會再來。",
    "name": "¿¿¿",
    "setTime": "2 週前",
    "star": 1
  },
  {
    "content": "",
    "name": "謙回",
    "setTime": "2 週前",
    "star": 5
  },
  {
    "content": "",
    "name": "洪智誠",
    "setTime": "2 週前",
    "star": 5
  },
  {
    "content": "",
    "name": "何秀美",
    "setTime": "2 週前",
    "star": 3
  },
  {
    "content": "𝕥𝕙𝕖 𝕓𝕖𝕤𝕥 𝕥𝕠𝕦𝕣𝕚𝕤𝕥 𝕒𝕥𝕥𝕣𝕒𝕔𝕥𝕚𝕠𝕟 …",
    "name": "jerry alceso",
    "setTime": "2 週前",
    "star": 5
  },
  {
    "content": "1.因為看到google評論滿滿的五顆星，所以覺得就算花200門票的錢入場還是很期待，但繞完一整個園區雖然門票可以折抵50塊紀念品和50塊客家米食體驗館的錢，三個月再去還可以兩人免費，但就會開始好奇到底打卡五星評論是送多好的禮物？我本人甚至一顆星都不想給^_^;\n2.網路上看到疫情前有養小馬跟羊駝，在評論區也有看到兔子跟麝香豬，但今天我們什麼都沒看到😅，只看到池塘裡的魚(*^_^*)\n3.客家米食我有試吃啦，我個人是覺得我家那邊賣的比較好吃，但這比較主觀，所以大家可以忽略這點\n4.市集裡賣的東西我覺得還不錯，但可能也沒必要買門票進來買。。\n5.拍照的景點很零散，看不出什麼主題性，而且每個建築你要說是復古風也不是，看起來就是髒髒舊舊的(@_@)\n6.園區內有提供免費的傘，讚ㄛ！\n7.從頭到尾很好奇琉璃仙境怎麼取的，根本毫無關聯🤔\n8.總體而言，這次來此地遊玩的經驗非常糟糕，我們花200塊進去然後待不到一小時就走了，感覺自己被網路騙慘了😭😭😭\n註：附圖為今天我跟我朋友學隔壁阿姨拍的照",
    "name": "傅郁",
    "setTime": "2 週前",
    "star": 1
  },
  {
    "content": "",
    "name": "鄭阿貴",
    "setTime": "2 週前",
    "star": 5
  },
  {
    "content": "琉璃仙境是個很好拍照的好地方 真的推薦可以來看看",
    "name": "艾情",
    "setTime": "2 週前",
    "star": 5
  },
  {
    "content": "今天我們來這裡看泰迪熊很好玩",
    "name": "Ocha Salsabila",
    "setTime": "2 週前",
    "star": 5
  },
  {
    "content": "今天來琉璃仙境、因爲彰化縣民所以免費！因爲假日天人蠻多的，很適合情侶拍照、小孩、全家一起遊玩的好地方！",
    "name": "廖銘棋",
    "setTime": "2 週前",
    "star": 5
  },
  {
    "content": "很美的地方 假日有熊貓表演實在非常好玩又有趣因為他們還會跳舞還有粉色教堂超級夢幻",
    "name": "陳亭聿",
    "setTime": "2 週前",
    "star": 5
  },
  {
    "content": "環境很美服務態度很好拍照留念好地方產品很好用乾淨舒適的空間",
    "name": "賴玉珊",
    "setTime": "2 週前",
    "star": 5
  },
  {
    "content": "琉璃仙境 好好玩  還有好好吃的冰\n還有熊貓表演  小孩超開心",
    "name": "陳雅鈴",
    "setTime": "2 週前",
    "star": 5
  },
  {
    "content": "好玩好照相好漂亮好可愛好玩 東西好吃 很涼快 好舒服的地方",
    "name": "李LeeFanny嘉芳",
    "setTime": "2 週前",
    "star": 5
  },
  {
    "content": "第一次帶老婆和兒子來這裏逛很好看 值得下次在來 這裏吃美食",
    "name": "葉峻瑋",
    "setTime": "2 週前",
    "star": 5
  },
  {
    "content": "第一次來這裡覺得風景不錯 值得在來拍照留念",
    "name": "慧寶貝",
    "setTime": "2 週前",
    "star": 5
  },
  {
    "content": "好適合來這拍照放鬆的好地方，小孩玩的很開心，非常乾淨^^",
    "name": "蘇明芬",
    "setTime": "2 週前",
    "star": 5
  },
  {
    "content": "這裡環境很好！而且廁所很涼，有冷氣，不會有臭味~到八月底前彰化縣民還可以不用門票，超優惠！！！",
    "name": "柯怡如",
    "setTime": "2 週前",
    "star": 5
  },
  {
    "content": "非常喜歡這裡，很夢幻，而且手鍊超好看的～～推薦大家來玩，他們也有提供雨傘可以遮陽擋雨，我覺得很用心🥰",
    "name": "Hsun Cheng",
    "setTime": "2 週前",
    "star": 5
  },
  {
    "content": "是一個適合各式年齡層來玩的一個休閒農場啊\n棒棒der",
    "name": "Dora yeh",
    "setTime": "2 週前",
    "star": 5
  },
  {
    "content": "需要門票可以接受，但食物價貴且份量超少，五星好評會送小禮",
    "name": "NICK C",
    "setTime": "2 週前",
    "star": 5
  },
  {
    "content": "流璃仙境真的是人間仙境，好吃好玩好地方大家快點來喔開心好避暑",
    "name": "丁百年",
    "setTime": "2 週前",
    "star": 5
  },
  {
    "content": "可能是初步佈置花比較稀疏，\n不過整體規劃上不錯，\n還有人演唱，演唱得很好聽！\n\n牆面還有建築拍照起來蠻好看的！",
    "name": "Lin Lin Chou",
    "setTime": "2 週前",
    "star": 5
  },
  {
    "content": "貓熊表演好精彩，大人小孩樂哈哈，蹦蹦跳跳好愉快",
    "name": "寶戀",
    "setTime": "2 週前",
    "star": 5
  },
  {
    "content": "這裡服務人員都非常友善，這裡的香皂，沐浴乳洗髮精都很好聞",
    "name": "林美慧",
    "setTime": "2 週前",
    "star": 5
  },
  {
    "content": "這個地方很美 很有味道 教堂也很漂亮 這裡也有很多地方很美 是個很好的地方!",
    "name": "卉卉tv",
    "setTime": "2 週前",
    "star": 5
  },
  {
    "content": "今天來琉璃仙境覺得這邊很好尤其在裡面吃飯自助式火鍋吃到飽的很好吃很值得討覽解說員服務很好很專業",
    "name": "邱麗婕",
    "setTime": "2 週前",
    "star": 5
  },
  {
    "content": "這邊有很多童話般的拍照背景，園區就有餐可以吃，很方便＾＾",
    "name": "洪嘉秀",
    "setTime": "2 週前",
    "star": 5
  },
  {
    "content": "園區很大，好逛～\n\n很適合網美來拍照、新人來拍婚紗唷！",
    "name": "黃小君",
    "setTime": "2 週前",
    "star": 5
  },
  {
    "content": "擁有許多漂亮美麗的景點，可以拍攝得很開心。",
    "name": "cony",
    "setTime": "2 週前",
    "star": 5
  },
  {
    "content": "超超超適合拍照的地方，各種異國風，還有粉紅宮殿，根本是小女孩們的夢想🥰",
    "name": "藍金魚",
    "setTime": "2 週前",
    "star": 5
  },
  {
    "content": "好的",
    "name": "Jimmy Sun",
    "setTime": "2 週前",
    "star": 5
  },
  {
    "content": "",
    "name": "葉騰仁",
    "setTime": "2 週前",
    "star": 5
  },
  {
    "content": "一個大園區有很多個區域可以拍照，每個建築都非常有特色，門票價格也很親民，是寵物友善園區，有帶龜龜一同造訪，玩的很開心，重點廁所有貼心冷氣！",
    "name": "王政興",
    "setTime": "2 週前",
    "star": 5
  },
  {
    "content": "第一次來這邊吃十二星座主題涵館，餐點好吃，景色優美，可以來這邊待一整天，重點評論廁所，有冷氣自動門，可以舒服的上廁所真的大推！而且我們有帶龜龜來散步，是寵物友善園區~很推薦有寵物的人來這邊玩！",
    "name": "王晨瑄",
    "setTime": "2 週前",
    "star": 5
  },
  {
    "content": "建築美麗，餐點可口，還有貼心的陽傘服務，是可以一遊的地點喔！",
    "name": "陳麗琴",
    "setTime": "2 週前",
    "star": 5
  },
  {
    "content": "一個超級適合親子旅遊的好地方，裡面的餐館也都超級好吃如果有來彰化一定要來這裡看看",
    "name": "王少岑",
    "setTime": "2 週前",
    "star": 5
  },
  {
    "content": "彰化縣民8月免費進場 有小動物 手工皂試用溜小孩好地方",
    "name": "趙正達",
    "setTime": "2 週前",
    "star": 5
  },
  {
    "content": "適合平日來走走逛逛，可以帶小孩子遛遛看看動物拍拍美照，\n也有好吃的美食及冰淇淋還可以逛逛手工肥皂真的是好去處。",
    "name": "魏瑜嫻",
    "setTime": "2 週前",
    "star": 5
  },
  {
    "content": "",
    "name": "張良田",
    "setTime": "2 週前",
    "star": 3
  },
  {
    "content": "帶著媽媽跟孫子來到這地方走走晃晃，很讚",
    "name": "王文秀",
    "setTime": "2 週前",
    "star": 5
  },
  {
    "content": "帶帶小孩來這裡非常非常棒，飲料也好好好喝讚👍。 …",
    "name": "彭小婷",
    "setTime": "2 週前",
    "star": 5
  },
  {
    "content": "這是一個很棒的地方，無論是求婚或是拍照都是強力推薦，特別是12星座水管屋，跟本說到我的心聲啊啊！強力推薦網美打卡拍照必來！",
    "name": "杜少Barry",
    "setTime": "2 週前",
    "star": 5
  },
  {
    "content": "",
    "name": "李有財",
    "setTime": "2 週前",
    "star": 5
  },
  {
    "content": "",
    "name": "Kido Hunag",
    "setTime": "2 週前",
    "star": 4
  },
  {
    "content": "這裡的星座餐廳來吃過兩回了，有自己舒適的冷氣房小空間，餐點份量超足夠，還會多贈送火鍋食材，不用點很多就飽足，cp值超高。\n服務人員快速又親切，讓人吃得安心舒適。\n園區雖小卻處處可拍，走的是精緻溫暖的路線。\n彰化縣民免門票，不論是餐點或景色，都值得來一趟。\n將來有朋友到彰化，我也非常推薦來這裡一遊。",
    "name": "李美文",
    "setTime": "2 週前",
    "star": 5
  },
  {
    "content": "服務態度很好",
    "name": "安晏陳",
    "setTime": "2 週前",
    "star": 5
  },
  {
    "content": "婚攝、晒小孩的好去處，有大球、大碗雪花冰跟夠涼的冷氣",
    "name": "Hong-Jhe Liu",
    "setTime": "2 週前",
    "star": 5
  },
  {
    "content": "環境優美，是值得大家一起出來遊玩散步的好地方",
    "name": "葉大仁",
    "setTime": "2 週前",
    "star": 5
  },
  {
    "content": "彰化人到8月底前入場不用錢 大家趕快來玩",
    "name": "吳俊諺",
    "setTime": "2 週前",
    "star": 5
  },
  {
    "content": "",
    "name": "游麗慧",
    "setTime": "2 週前",
    "star": 5
  },
  {
    "content": "超夢幻的拍照景點，處處有美景餐點美食也好吃.",
    "name": "蔡幸芳",
    "setTime": "3 週前",
    "star": 5
  },
  {
    "content": "第一次來這裏，感覺真的很不錯拍照也很胖棒",
    "name": "老王",
    "setTime": "3 週前",
    "star": 5
  },
  {
    "content": "這裡很好拍，可推薦可以來這裡走走拍照",
    "name": "張玉子",
    "setTime": "3 週前",
    "star": 5
  },
  {
    "content": "第一次來琉璃仙境這裡不錯",
    "name": "黃錦緞",
    "setTime": "3 週前",
    "star": 5
  },
  {
    "content": "市集的小姐很親切 導覽樂樂很可愛",
    "name": "黃玉珠",
    "setTime": "3 週前",
    "star": 5
  },
  {
    "content": "服務人員nice，廁所yyds",
    "name": "TO AA",
    "setTime": "3 週前",
    "star": 5
  },
  {
    "content": "",
    "name": "吳栩臻",
    "setTime": "3 週前",
    "star": 5
  },
  {
    "content": "餐點好吃又小朋友又玩的開心🥳\n真是大小朋友適合來的親子地方👍🏻👍🏻 …",
    "name": "李宜玲",
    "setTime": "3 週前",
    "star": 5
  },
  {
    "content": "可能到訪人數不多，環境管理有進步空間，夏季熱的無處躲藏，蚊子更是嚇人的多。",
    "name": "許麗崋",
    "setTime": "3 週前",
    "star": 3
  },
  {
    "content": "這裡很好玩因為有冷氣吹又有很多東西可以買",
    "name": "高小辰",
    "setTime": "3 週前",
    "star": 5
  },
  {
    "content": "這裡很好玩因為有很多東西可以買裡面的冷氣又很涼",
    "name": "莊美月",
    "setTime": "3 週前",
    "star": 5
  },
  {
    "content": "",
    "name": "郭齊",
    "setTime": "3 週前",
    "star": 5
  },
  {
    "content": "感覺不太算是農場 應該是偏向拍婚紗的地方 記得做好防蟲的措施 進來約20分鐘被叮了四個包 有的天竺鼠身上有傷口 因為是平日來 很多都沒開放 也許假日來會不一樣吧 8/31前彰化縣民免費",
    "name": "tofu",
    "setTime": "3 週前",
    "star": 3
  },
  {
    "content": "",
    "name": "Shou Chien Lin",
    "setTime": "3 週前",
    "star": 4
  },
  {
    "content": "拍照的好地方",
    "name": "林妙真",
    "setTime": "3 週前",
    "star": 5
  },
  {
    "content": "為什麼只開到五點半，問號",
    "name": "阿基米德",
    "setTime": "3 週前",
    "star": 5
  },
  {
    "content": "粉紅教堂很夢幻，很適合家庭旅遊！推薦大家～",
    "name": "Ariel Kuo",
    "setTime": "3 週前",
    "star": 5
  },
  {
    "content": "市集的東西很好買，風景優美很好拍照",
    "name": "永署張",
    "setTime": "3 週前",
    "star": 5
  },
  {
    "content": "地方優美，服務人員服務態度很好，非常推薦大家來",
    "name": "黃焜",
    "setTime": "3 週前",
    "star": 5
  },
  {
    "content": "門票200\n有天竺鼠\n有泡腳池",
    "name": "吳美鳳",
    "setTime": "3 週前",
    "star": 3
  },
  {
    "content": "有魚池可以餵魚，空間很大假日也有表演。很適合拍照打卡",
    "name": "XUAN",
    "setTime": "3 週前",
    "star": 5
  },
  {
    "content": "週末假日親子旅遊的好去處，小孩子玩的好快樂，又有好吃的東西，真是不錯的好去處。",
    "name": "mei chi",
    "setTime": "3 週前",
    "star": 5
  },
  {
    "content": "這裡風景好很適合來散步，服務人員態度很好，還可以拍很多照片，彰化市民免費唷",
    "name": "謝忠明",
    "setTime": "3 週前",
    "star": 5
  },
  {
    "content": "好玩好拍\n很美麗的打卡景點\n很nice隨處還有遮陽傘可以使用",
    "name": "candy shiu",
    "setTime": "3 週前",
    "star": 5
  },
  {
    "content": "空間很大 風景很漂亮很適合拍照📷東西也都可以適用👍🏻 …",
    "name": "許漢穎",
    "setTime": "3 週前",
    "star": 5
  },
  {
    "content": "老闆娘很漂亮，下午來很舒服適合拍照踏青，今天也拍了很多照片。",
    "name": "容",
    "setTime": "3 週前",
    "star": 5
  },
  {
    "content": "適合親子前來遊玩，不僅有吃也要喝的項目可以做選擇甚至還有冰品",
    "name": "陳敬佑",
    "setTime": "3 週前",
    "star": 5
  },
  {
    "content": "",
    "name": "李尤宜",
    "setTime": "3 週前",
    "star": 5
  },
  {
    "content": "很漂亮，拍照吃飯溜小孩的好地方，8／31前彰化縣民免門票",
    "name": "蔡孟昌",
    "setTime": "3 週前",
    "star": 5
  },
  {
    "content": "裡面很乾淨還有熊貓表演，很適合小孩...8/31之前彰化縣民不用門票，值得大家來逛逛",
    "name": "李俞瑩",
    "setTime": "3 週前",
    "star": 5
  },
  {
    "content": "真的很適合來拍美美婚紗照的地方\n連廁所也很夢幻😂超好拍吶~~\n婚攝聖地 …",
    "name": "張子建",
    "setTime": "3 週前",
    "star": 5
  },
  {
    "content": "琉璃仙境真的太漂亮了，適合全家大小來遊玩，真是太讚了！",
    "name": "蔡美滿",
    "setTime": "3 週前",
    "star": 5
  },
  {
    "content": "很可愛的景點\n值得來逛逛唷😊\n香氛吊飾\n可愛美麗的建築 …",
    "name": "Pin ling Huang",
    "setTime": "3 週前",
    "star": 5
  },
  {
    "content": "趕快帶小孩來走走，市集裡面的服務生很親切有禮貌 但是天氣好熱啊😅 …",
    "name": "許薾勻",
    "setTime": "3 週前",
    "star": 5
  },
  {
    "content": "彰化縣民八月底免門票喔！環境漂亮",
    "name": "洪聰和",
    "setTime": "3 週前",
    "star": 5
  },
  {
    "content": "小禮物真實用又好看，推～\n這裡的香皂都很香喔，耶！",
    "name": "儒儒",
    "setTime": "3 週前",
    "star": 5
  },
  {
    "content": "原始森林香氛沐浴乳可以用門票折50元真划算哦",
    "name": "Abi",
    "setTime": "3 週前",
    "star": 5
  },
  {
    "content": "適合親子同樂用餐的地點，假日可以全家來用餐並且逛逛喔",
    "name": "Zhen-Kai Lin",
    "setTime": "3 週前",
    "star": 5
  },
  {
    "content": "餐點不錯吃，環境也維護的很好！\n還有駐唱歌手整體氛圍不錯",
    "name": "楊星儀",
    "setTime": "3 週前",
    "star": 5
  },
  {
    "content": "超好拍的網美景點，快來踩點！\n還有彰化鄉親免門票唷！",
    "name": "蘇翠華",
    "setTime": "3 週前",
    "star": 4
  },
  {
    "content": "很漂亮的地方大家可以一起找親朋好友來喔",
    "name": "何松諺",
    "setTime": "3 週前",
    "star": 5
  },
  {
    "content": "兒子超愛沙坑…廁所很乾淨…城堡造景很漂亮…還有現場音樂可以聽~~~",
    "name": "施雅青",
    "setTime": "3 週前",
    "star": 5
  },
  {
    "content": "",
    "name": "曾彥維",
    "setTime": "3 週前",
    "star": 4
  },
  {
    "content": "三個小美女第一次見面就這麼開心～\n下次見面不知道什麼時候了～\n難得彰化縣民八月底前不用門票🎫\n可惜我戶籍地已經不在彰化了，所以要門票。 …",
    "name": "Elys Huang",
    "setTime": "3 週前",
    "star": 5
  },
  {
    "content": "大草地小朋友可以跑跳，\n拍照景點多到數不清，\n還有一個特色，\n廁所比室外涼喔！",
    "name": "郭芯箖",
    "setTime": "3 週前",
    "star": 5
  },
  {
    "content": "獨立包廂吃鴛鴦鍋\n超棒體驗\n裡面也是美噠噠\n粉紅雨白色教堂超夢幻",
    "name": "徐曉婷",
    "setTime": "3 週前",
    "star": 5
  },
  {
    "content": "好逛、好玩、好拍照的地方～\n\n服務人員很親切\n\n適合大小朋友來遊玩",
    "name": "郭銘洧",
    "setTime": "3 週前",
    "star": 5
  },
  {
    "content": "東西很好吃，門票還能抵消費，店員很親切，商品優質，是家庭旅遊的好去處",
    "name": "施永恩",
    "setTime": "3 週前",
    "star": 5
  },
  {
    "content": "餐點好吃不貴，園區漂亮好看又好拍，香氛吊飾不錯，服務人員超親切，可以再來玩",
    "name": "Kawai kuo",
    "setTime": "3 週前",
    "star": 5
  },
  {
    "content": "很多地方可拍照打卡，市集內有護手霜、香氛涼香膏、香皂、洗髮精、沐浴乳、護髮素等等，味道都很好聞",
    "name": "施勝順",
    "setTime": "3 週前",
    "star": 5
  },
  {
    "content": "餐點好吃又便宜，門票還可折抵市集商品，香氛吊飾有多種味道可選擇",
    "name": "施庭嬅",
    "setTime": "3 週前",
    "star": 5
  },
  {
    "content": "停車方便，園區空間大造景用心打理，餐食多選擇，適合全家走走。",
    "name": "T H",
    "setTime": "3 週前",
    "star": 5
  },
  {
    "content": "有很多很漂亮可以打卡的風景，環境很棒，火鍋有咖哩跟原味的圓形鴛鴦鍋很特別！",
    "name": "陳雪琴",
    "setTime": "3 週前",
    "star": 5
  },
  {
    "content": "一走入園區便聞到淡淡香味，裡頭多樣化的造型更是引人注目！",
    "name": "蔆蔆",
    "setTime": "3 週前",
    "star": 5
  },
  {
    "content": "這裡很好玩請大家來玩玩，吃的也很好吃，讚讚讚",
    "name": "李建宏",
    "setTime": "3 週前",
    "star": 5
  },
  {
    "content": "這裡很好玩商品很有趣我們很喜歡到這裡來客服人員也很客氣哈哈我要+1",
    "name": "李紹章",
    "setTime": "3 週前",
    "star": 5
  },
  {
    "content": "這裡很棒",
    "name": "劉素芬",
    "setTime": "3 週前",
    "star": 5
  },
  {
    "content": "冰淇淋好吃，花草優美，用心經營、值得推薦的好去處。",
    "name": "李瓊音",
    "setTime": "3 週前",
    "star": 5
  },
  {
    "content": "景色優美，適合全家大小出遊走走，放暑假的好地方！",
    "name": "陳玉樺",
    "setTime": "3 週前",
    "star": 5
  },
  {
    "content": "這裡景點很漂亮很推薦來這裏走走拍照",
    "name": "陳何美芳",
    "setTime": "3 週前",
    "star": 5
  },
  {
    "content": "琉璃仙境戰戰戰實在太美了有機會一定要來走一趟喔",
    "name": "何秋玫",
    "setTime": "3 週前",
    "star": 5
  },
  {
    "content": "真實的是個好景點，不來太可惜了",
    "name": "詹鳳珠",
    "setTime": "3 週前",
    "star": 5
  },
  {
    "content": "值得來琉璃仙境很棒喔風景好服務親切值得來玩",
    "name": "李姿慧",
    "setTime": "3 週前",
    "star": 5
  },
  {
    "content": "第一站就開始採購，也是拍照的好地點，導覽人員解說超讚的呦",
    "name": "Meigo Wu",
    "setTime": "3 週前",
    "star": 5
  },
  {
    "content": "拍照好地方，導覽人員讚，適合全家大小一起來旅遊",
    "name": "李英雀",
    "setTime": "3 週前",
    "star": 5
  },
  {
    "content": "風景優美網拍好地點服務人員親切又美麗讚讚",
    "name": "吳伯伯",
    "setTime": "3 週前",
    "star": 5
  },
  {
    "content": "很適合拍照風景優美廁所冷氣很涼喔來吹吹看喔",
    "name": "吳佳霓",
    "setTime": "3 週前",
    "star": 5
  },
  {
    "content": "環境優美動線流暢商品多多好拍照有空歡迎來逛逛",
    "name": "曾居文",
    "setTime": "3 週前",
    "star": 5
  },
  {
    "content": "讚喔！",
    "name": "曹惠文",
    "setTime": "3 週前",
    "star": 5
  },
  {
    "content": "服務人員態度很好。這裡很適合全家大小一起出遊用餐走走！",
    "name": "曾月麗",
    "setTime": "3 週前",
    "star": 5
  },
  {
    "content": "服務親切，產品價格實在，環境優美，贊贊贊，",
    "name": "呂美齡",
    "setTime": "3 週前",
    "star": 5
  },
  {
    "content": "服務態度很好啦，購買環境優雅，很棒的場所。",
    "name": "慕秀華",
    "setTime": "3 週前",
    "star": 5
  },
  {
    "content": "環境優美 有各種奇特的造型建築 還有餐廳美食",
    "name": "郭淑真",
    "setTime": "3 週前",
    "star": 5
  },
  {
    "content": "環境優美，左手香舒緩涼香膏很涼很好用，可防蚊喔！",
    "name": "銀市潘",
    "setTime": "3 週前",
    "star": 5
  },
  {
    "content": "廁所有冷氣.服務員人親切又熱.心.東西又.實.用讚",
    "name": "黃素綢",
    "setTime": "3 週前",
    "star": 5
  },
  {
    "content": "環境優美、服務品質好、動線規劃完整，適合遊玩的地方。",
    "name": "Vanessa WU",
    "setTime": "3 週前",
    "star": 5
  },
  {
    "content": "服務優良親切品質優良希望親朋好友共同光臨",
    "name": "K.M Liao",
    "setTime": "3 週前",
    "star": 5
  },
  {
    "content": "風景優美，網美推推推！服務人員親切又美麗！👍👍👍 …",
    "name": "杜曉蓉",
    "setTime": "3 週前",
    "star": 5
  },
  {
    "content": "服務親切風景優美,流連忘懷在此心曠神怡，產品好用價錢合理。",
    "name": "劉湄蓁",
    "setTime": "3 週前",
    "star": 5
  },
  {
    "content": "產品好用，服務人員很好，樂樂導覽員服務很好。",
    "name": "張玉鳳",
    "setTime": "3 週前",
    "star": 5
  },
  {
    "content": "環境優美，適合辦理婚禮，服務人員很親切，很棒的地方。",
    "name": "Chang Sue",
    "setTime": "3 週前",
    "star": 5
  },
  {
    "content": "風景很漂亮那個產品更好，雨傘也很漂亮好用",
    "name": "徐阿珉",
    "setTime": "3 週前",
    "star": 5
  },
  {
    "content": "風景漂亮產品也不錯喔服務人員很親切，",
    "name": "謝美玲",
    "setTime": "3 週前",
    "star": 5
  },
  {
    "content": "今天下午去走走，售票口服務小姐親切美麗～",
    "name": "Richard Huang",
    "setTime": "3 週前",
    "star": 5
  },
  {
    "content": "國際獅子會台灣總會\n2020-2021年度內閣到此一遊\n到琉璃仙境拍下拍美的照片",
    "name": "陳麗鳳",
    "setTime": "3 週前",
    "star": 5
  },
  {
    "content": "琉璃仙境值得一遊，尤其有五星級廁所，有冷氣喔？！",
    "name": "黃進財",
    "setTime": "3 週前",
    "star": 5
  },
  {
    "content": "如果有六星我想打六星服務真的太好了",
    "name": "張樹林",
    "setTime": "3 週前",
    "star": 5
  },
  {
    "content": "琉璃仙境好玩環境優美服務親切服務人員美又可愛超級讚",
    "name": "楊政義",
    "setTime": "3 週前",
    "star": 5
  },
  {
    "content": "場景新穎、照相背景多樣化、解說小姐（樂樂）親切可愛、園區服務人員漂亮又耐心。",
    "name": "陳秋欽",
    "setTime": "3 週前",
    "star": 5
  },
  {
    "content": "琉璃仙境是個好地方景色漂亮，服務人員服務很好！很適合來這裏遊玩",
    "name": "葉寒青",
    "setTime": "3 週前",
    "star": 5
  },
  {
    "content": "琉璃仙境～真的很美很漂亮的打卡景點\n服務人員很親切，可愛",
    "name": "高鳳儀",
    "setTime": "3 週前",
    "star": 5
  },
  {
    "content": "第一次來到流璃仙境，感受到服務美妹待人親和力，園內值得逛逛拍照。",
    "name": "廖有諒",
    "setTime": "3 週前",
    "star": 5
  },
  {
    "content": "琉璃仙境很漂亮又很好玩下次大家一起來玩喔這裡也很適合來這裡拍照",
    "name": "許敏益",
    "setTime": "3 週前",
    "star": 5
  },
  {
    "content": "琉璃仙境很漂亮小姐的服務又好長得又漂亮希望大家下次來玩",
    "name": "陳國明",
    "setTime": "3 週前",
    "star": 5
  },
  {
    "content": "琉璃仙境很漂亮服務又好長得漂亮。很適合來這裡拍照打卡",
    "name": "范秋麗",
    "setTime": "3 週前",
    "star": 5
  },
  {
    "content": "琉璃仙境很漂亮小姐的服務又好長得又漂亮希望大家下次來玩",
    "name": "kiki",
    "setTime": "3 週前",
    "star": 5
  },
  {
    "content": "大人小孩都很適合來的地方\n很多景點可以拍照\n裡面的建築很漂亮",
    "name": "Chia Hsu",
    "setTime": "3 週前",
    "star": 5
  },
  {
    "content": "好吃好玩",
    "name": "黃苡榕",
    "setTime": "4 週前",
    "star": 5
  },
  {
    "content": "火鍋很好吃🫰\n很好拍～～～～～\n適合情侶、全家一起來❤️ …",
    "name": "Shirley Yen",
    "setTime": "4 週前",
    "star": 5
  },
  {
    "content": "這裡很漂亮很適合帶小朋友來這裡玩，也很適合來這裡拍照",
    "name": "宜鈞大大",
    "setTime": "4 週前",
    "star": 5
  },
  {
    "content": "",
    "name": "陳冬雄",
    "setTime": "4 週前",
    "star": 5
  },
  {
    "content": "服務人員親切\n適合婚紗拍攝、婚宴\n還可以蕾茶\n是還帶小孩出遊",
    "name": "蕭人慈",
    "setTime": "4 週前",
    "star": 5
  },
  {
    "content": "園區很大喔！很多場景可以拍照、環境維護用心、可以跟家人來走一走拍拍照👍🏻 …",
    "name": "Chiao",
    "setTime": "4 週前",
    "star": 5
  },
  {
    "content": "園區很好拍，適合遛小孩，還有泡腳池，彈力球等等可以親子互動.",
    "name": "Chiao Chiao",
    "setTime": "4 週前",
    "star": 5
  },
  {
    "content": "很可愛的景點\n值得來逛逛唷～\n內有手工皂\n香氛吊飾\n可愛美麗的建築",
    "name": "鄭淑引",
    "setTime": "4 週前",
    "star": 5
  },
  {
    "content": "真是一個大人&小孩都適合來的地方、喜歡裡面的動線、而且用餐環境優雅知性舒適。😀 …",
    "name": "黄家蓁",
    "setTime": "4 週前",
    "star": 5
  },
  {
    "content": "很浪漫的景點很適合拍照又有很多小禮物可以買",
    "name": "杜麗英",
    "setTime": "4 週前",
    "star": 5
  },
  {
    "content": "到處都是拍照的好定點然後還可以泡腳然後還可以踢球然後呢到處都充滿了驚奇太棒了",
    "name": "洪錦貴",
    "setTime": "4 週前",
    "star": 5
  },
  {
    "content": "這個地方很漂亮打卡的地方也很多沒個角落都很好拍",
    "name": "洪宥瑄",
    "setTime": "4 週前",
    "star": 5
  },
  {
    "content": "彰化又有一個新景點，相信過年一定非常熱鬧",
    "name": "楊先生",
    "setTime": "4 週前",
    "star": 5
  },
  {
    "content": "",
    "name": "洪靜如",
    "setTime": "1 個月前",
    "star": 5
  },
  {
    "content": "有白色教堂、粉紅色神殿、哈比屋、12星座水管屋，都是非常特別好玩！",
    "name": "有帥",
    "setTime": "1 個月前",
    "star": 5
  },
  {
    "content": "天氣很好拍起來很漂亮，適合親子一起來旅遊！目前彰化縣民免費唷！快來走走",
    "name": "林昆誼",
    "setTime": "1 個月前",
    "star": 5
  },
  {
    "content": "天氣很熱但很可以逛唷！！\n非常多景點可以拍～～讚讚讚推薦👍",
    "name": "Jia Ying Lin",
    "setTime": "1 個月前",
    "star": 5
  },
  {
    "content": "服務人員親切，餐廳有多種風格選擇，適合假日全家大小一起遊玩❤️",
    "name": "Nen jiang",
    "setTime": "1 個月前",
    "star": 5
  },
  {
    "content": "彰化推薦親子出遊的好地方～ 可以吃又可以玩讓小孩放電的好地方😊 …",
    "name": "HL T",
    "setTime": "1 個月前",
    "star": 5
  },
  {
    "content": "餐點好吃 遊樂設施好玩 還有泡腳池 夏天來的好地方",
    "name": "詹健挺",
    "setTime": "1 個月前",
    "star": 5
  },
  {
    "content": "溜小孩的好地方！有大草皮可以奔跑跟踢球，玩餓了還有餐廳可以用餐。",
    "name": "陳靜芬",
    "setTime": "1 個月前",
    "star": 5
  },
  {
    "content": "這邊很漂亮也很好逛 可以遛小孩 裡面還有附洗澡的不用怕小孩沒地方換衣服👍🏻 …",
    "name": "蠟筆小新",
    "setTime": "1 個月前",
    "star": 5
  },
  {
    "content": "假日時間可以帶小朋友,來這邊走走泡泡腳還有小動物，進來玻璃市集還有很多香水肥皂可以買。",
    "name": "蔡站已",
    "setTime": "1 個月前",
    "star": 5
  },
  {
    "content": "適合親子同樂的好地方。有餐廳可以填飽肚子，有泡腳區玩沙區可以放電！超棒的！推薦大家來玩",
    "name": "蔡宜玲",
    "setTime": "1 個月前",
    "star": 5
  },
  {
    "content": "很好玩，很好拍，很好吃。",
    "name": "陳佳琳",
    "setTime": "1 個月前",
    "star": 5
  },
  {
    "content": "有補集乳室非常貼心，而且裡面有冷氣洗手台，香香的，非常乾淨，友善的環境！適合親子",
    "name": "CHIN-HSIU YANG",
    "setTime": "1 個月前",
    "star": 5
  },
  {
    "content": "好玩，非常值得再來！\n有玩有看又有吃，很有趣！\n推薦大家。",
    "name": "N HSU",
    "setTime": "1 個月前",
    "star": 5
  },
  {
    "content": "拍照好地方，很多好看彩繪牆，棒棒滴~",
    "name": "Bella Husi",
    "setTime": "1 個月前",
    "star": 5
  },
  {
    "content": "有免費停車場停車很方便喔～景觀優美適合拍照！",
    "name": "李美村",
    "setTime": "1 個月前",
    "star": 5
  },
  {
    "content": "112.8.31前彰化縣民免費，附設免費停車場，真是假日休閒好去處～",
    "name": "謝宜婷",
    "setTime": "1 個月前",
    "star": 5
  },
  {
    "content": "有附設免費停車場，環境優美且有草皮適合小孩玩耍！",
    "name": "謝宜霖",
    "setTime": "1 個月前",
    "star": 5
  },
  {
    "content": "環境感覺很好，人多也不擁擠，有育嬰及擠哺乳室，適合帶小朋友來",
    "name": "陳柏愷",
    "setTime": "1 個月前",
    "star": 5
  },
  {
    "content": "很不錯地方，很適合小朋友來玩,帶老人來泡腳也不錯",
    "name": "steven chen",
    "setTime": "1 個月前",
    "star": 5
  },
  {
    "content": "這裡真的很好玩，也很好拍照，還有很多手工皂可以適用，是很棒的地方",
    "name": "陳姵緁",
    "setTime": "1 個月前",
    "star": 5
  },
  {
    "content": "琉璃仙境園區，員工熱誠服務，東西非常不錯，值得大家來購買及遊園。",
    "name": "鄭金城",
    "setTime": "1 個月前",
    "star": 5
  },
  {
    "content": "這裡就是琉璃仙境，很好玩的地方，樂樂妹妹好可愛，又親切，東西好用，又便宜。",
    "name": "黃剛健",
    "setTime": "1 個月前",
    "star": 5
  },
  {
    "content": "琉璃探索地方好玩東西好用妹妹好可愛服務人員親切可愛漂亮",
    "name": "古一樣",
    "setTime": "1 個月前",
    "star": 5
  },
  {
    "content": "很好拍，風景很漂亮，整理得很乾淨，服務妹妹也很漂亮",
    "name": "林惠倩",
    "setTime": "1 個月前",
    "star": 5
  },
  {
    "content": "很好拍 風景漂亮 ，整理的非常乾淨。 服務人員也漂亮",
    "name": "陳惠美",
    "setTime": "1 個月前",
    "star": 5
  },
  {
    "content": "親子同樂，拍照景點多",
    "name": "江敏嘉",
    "setTime": "1 個月前",
    "star": 5
  },
  {
    "content": "兒童球池很適合帶小孩放電，還能拍攝美照",
    "name": "黃育玫",
    "setTime": "1 個月前",
    "star": 5
  },
  {
    "content": "網美景點適合親子同樂",
    "name": "A C",
    "setTime": "1 個月前",
    "star": 5
  },
  {
    "content": "很好很棒棒下次一定要再來玩",
    "name": "王狗狗",
    "setTime": "1 個月前",
    "star": 5
  },
  {
    "content": "很好的地方很棒棒一定要來玩",
    "name": "王奕笙",
    "setTime": "1 個月前",
    "star": 5
  },
  {
    "content": "",
    "name": "林志豪",
    "setTime": "1 個月前",
    "star": 3
  },
  {
    "content": "好拍打卡景點，餐點食材新鮮",
    "name": "Yuanchin Chen",
    "setTime": "1 個月前",
    "star": 5
  },
  {
    "content": "",
    "name": "綠小丸子",
    "setTime": "1 個月前",
    "star": 5
  },
  {
    "content": "東西好用",
    "name": "邱世昌",
    "setTime": "1 個月前",
    "star": 5
  },
  {
    "content": "好看好風景",
    "name": "賴冠廷",
    "setTime": "1 個月前",
    "star": 5
  },
  {
    "content": "",
    "name": "王小元（telnetjess）",
    "setTime": "1 個月前",
    "star": 5
  },
  {
    "content": "東西好吃好拍好好玩\n下午有機會一定要天氣好來",
    "name": "徐珮芳",
    "setTime": "1 個月前",
    "star": 5
  },
  {
    "content": "",
    "name": "王昱祥",
    "setTime": "1 個月前",
    "star": 4
  },
  {
    "content": "",
    "name": "張金和",
    "setTime": "1 個月前",
    "star": 1
  },
  {
    "content": "",
    "name": "Ming Jau",
    "setTime": "1 個月前",
    "star": 3
  },
  {
    "content": "不錯",
    "name": "楊少強",
    "setTime": "1 個月前",
    "star": 5
  },
  {
    "content": "遛小孩的好地方",
    "name": "林幸榆",
    "setTime": "1 個月前",
    "star": 5
  },
  {
    "content": "景觀美麗",
    "name": "顏子賢",
    "setTime": "1 個月前",
    "star": 5
  },
  {
    "content": "服務人員親切，很多超美的地方可以拍照，很適合全家大小一起來當網美",
    "name": "Catherine chen",
    "setTime": "1 個月前",
    "star": 5
  },
  {
    "content": "賣香氛服務人員很棒很貼心，小孩玩的很開心！\n推薦來玩玩！",
    "name": "徐小桂",
    "setTime": "1 個月前",
    "star": 5
  },
  {
    "content": "服務費收的非常合理。\n每個服務員都很親切熱情。\n餐廳不限時間。\n低消150／人。\n可以到處拍拍，然後再去餐廳吃飯喝飲料吹冷氣",
    "name": "M M",
    "setTime": "1 個月前",
    "star": 5
  },
  {
    "content": "這裡帶小朋友來走走，小孩還蠻開心的，很不錯！",
    "name": "黃惠玲",
    "setTime": "1 個月前",
    "star": 5
  },
  {
    "content": "地方好找好停車，還可以拍美美的照片，孩子也很開心留下美美的回憶",
    "name": "BEN LEE",
    "setTime": "1 個月前",
    "star": 5
  },
  {
    "content": "這裡是個很棒的地方，所有的建築都很漂亮，風景也很棒很適合拍照打卡",
    "name": "馬拉松漢堡",
    "setTime": "1 個月前",
    "star": 5
  },
  {
    "content": "很好看，很好拍，各種景點都很漂亮，會送折扣卷。",
    "name": "李佳欣",
    "setTime": "1 個月前",
    "star": 5
  },
  {
    "content": "雖然白天來，太陽非常大，但是還是拍了很多美美的照片，如果黃昏時間應該更為舒適。是放鬆的好地方",
    "name": "吳怡慧",
    "setTime": "1 個月前",
    "star": 5
  },
  {
    "content": "200塊入門票，園區非常小，幾乎30分鐘內就可以看完。\n沒有什麼主題規劃的感覺，就是一個又一個的人造建築，有點不知所云...要說是網美打卡聖地也不太像，因為沒有主題性、也沒什麼互動性的設施....\n如果要拍婚紗之類的照片，有很多其他很棒的選擇，像薰衣草森林、奇美博物館、鹿港老街等等，隨便一個拍出來的畫面都比這裡優質，外縣市遊客真的不用浪費時間過來！",
    "name": "秀",
    "setTime": "1 個月前",
    "star": 1
  },
  {
    "content": "環境優美的 餐點非常新鮮好吃 下次還要再來",
    "name": "蘇小燕",
    "setTime": "1 個月前",
    "star": 5
  },
  {
    "content": "琉璃仙境是一個好地方庭園美麗舒爽涼爽琉璃仙境是一個好地方庭園美麗又舒服餐點好吃招待人員親切服務熱誠真是好",
    "name": "顏秋滿",
    "setTime": "1 個月前",
    "star": 5
  },
  {
    "content": "真是拍照的好景點，餐飲一級棒，衛生設備真乾淨",
    "name": "陳伶芬",
    "setTime": "1 個月前",
    "star": 5
  },
  {
    "content": "餐點好吃 拍照好看下次再來",
    "name": "江威廷",
    "setTime": "1 個月前",
    "star": 5
  },
  {
    "content": "風景很漂亮 環境很漂亮廁所很美 讚 樂樂服務員好",
    "name": "洪春和",
    "setTime": "1 個月前",
    "star": 5
  },
  {
    "content": "五星級廁所很很涼爽 建築物拍照拍照好看",
    "name": "郭金保",
    "setTime": "1 個月前",
    "star": 5
  },
  {
    "content": "好漂亮的琉璃仙境還有五星級的廁所，太棒了",
    "name": "王清進王清進",
    "setTime": "1 個月前",
    "star": 5
  },
  {
    "content": "火鍋很好吃 服務很好導覧人員樂樂很漂亮",
    "name": "陳建名",
    "setTime": "1 個月前",
    "star": 5
  },
  {
    "content": "東西好吃\n風景漂亮",
    "name": "冠霖邱",
    "setTime": "1 個月前",
    "star": 5
  },
  {
    "content": "東西好吃很適合拍照服務人員很漂亮很親切",
    "name": "黃先持",
    "setTime": "1 個月前",
    "star": 5
  },
  {
    "content": "園區值得再來，拍照景點好，服務人員服務態度好",
    "name": "王春菊",
    "setTime": "1 個月前",
    "star": 5
  },
  {
    "content": "好拍照的地方 熊貓跳舞好可愛👍 …",
    "name": "豆豆",
    "setTime": "1 個月前",
    "star": 5
  },
  {
    "content": "真的很適合來拍美美婚紗照的地方！！\n超好拍吶~~還有泡腳區",
    "name": "Mama Yearu",
    "setTime": "1 個月前",
    "star": 5
  },
  {
    "content": "環境舒適，廁所很乾淨，工作人員服務態度好很親切",
    "name": "許晉睿",
    "setTime": "1 個月前",
    "star": 5
  },
  {
    "content": "食物好吃，香皂很香，洗完非常舒服，導覽人員親切友善。",
    "name": "許俊翔",
    "setTime": "1 個月前",
    "star": 5
  },
  {
    "content": "好美好美好美好美好美好美好美好美好美好美",
    "name": "張星星",
    "setTime": "1 個月前",
    "star": 5
  },
  {
    "content": "第一次來環境很好適合拍照網美好地方下次還會再來拍照好美",
    "name": "怡芳陳",
    "setTime": "1 個月前",
    "star": 5
  },
  {
    "content": "環境很舒適，導覽人員很親切，香氛香皂很天然，送人自用都合適。",
    "name": "詩媛",
    "setTime": "1 個月前",
    "star": 5
  },
  {
    "content": "園區漂亮 好玩 好逛\n東西好吃，肥皂好洗，香氛很香",
    "name": "鄧宏緯",
    "setTime": "1 個月前",
    "star": 5
  },
  {
    "content": "",
    "name": "邱淑華",
    "setTime": "1 個月前",
    "star": 4
  },
  {
    "content": "環境漂亮，適合放風拍照的好地方，服務人員服務態度好。",
    "name": "Yumi醬",
    "setTime": "1 個月前",
    "star": 5
  },
  {
    "content": "涵館用餐舒適涼爽！冷氣特強。",
    "name": "李文生",
    "setTime": "1 個月前",
    "star": 4
  },
  {
    "content": "趁現在彰化縣民免門票，趕快帶小孩來走走，市集裡面的服務生很親切有禮貌～",
    "name": "黃士銘",
    "setTime": "1 個月前",
    "star": 5
  },
  {
    "content": "",
    "name": "簡素真",
    "setTime": "1 個月前",
    "star": 3
  },
  {
    "content": "",
    "name": "Ray Wang",
    "setTime": "1 個月前",
    "star": 5
  },
  {
    "content": "售票員真的要員工教育訓練下，買票的優惠規則都自己寫了，爲什麼遊客出示身心障礙手冊的人，說不行依照全票賣？那不如不要這樣寫，這樣的心情都被打壞了",
    "name": "黃小甄",
    "setTime": "1 個月前",
    "star": 3
  },
  {
    "content": "環境優美清潔好拍照是網美景點，適合大人小孩全家的景點，餐點也方便",
    "name": "Shujuan Lin",
    "setTime": "1 個月前",
    "star": 5
  },
  {
    "content": "貼心的服務提供大陽傘☂️艷陽高照的天氣\n網美照非常適合 美麗的地方",
    "name": "黃惠貞",
    "setTime": "1 個月前",
    "star": 5
  },
  {
    "content": "園區很多好玩的還有適合拍照的地方，環境優美👍 …",
    "name": "Chun Yi",
    "setTime": "1 個月前",
    "star": 5
  },
  {
    "content": "環境很好 但是我真的覺得售票人員要好好的處理客人買票的需求 前面客人都出示身障手冊了 還問是不是設籍彰化的市民？ 然後就一樣買全票！那門口優待票的條件就只要寫限彰化市民就好 不要寫有身障手冊及陪同人員",
    "name": "劉力佳",
    "setTime": "1 個月前",
    "star": 4
  },
  {
    "content": "網美勝地，可以帶小孩來玩水泡腳，累了可以到餐廳吃飯！",
    "name": "林奕妘",
    "setTime": "1 個月前",
    "star": 5
  },
  {
    "content": "一家大小都很適合的場所，也很適合的親子互動的場所在琉璃仙境",
    "name": "陳秋樺",
    "setTime": "1 個月前",
    "star": 5
  },
  {
    "content": "園區內有沙坑泡腳池,適合親子遊玩,聚餐的好地方！",
    "name": "楊宜庭",
    "setTime": "1 個月前",
    "star": 5
  },
  {
    "content": "園區很大  小朋友在泡腳池玩得很開心，\n哺乳室非常舒適",
    "name": "萍",
    "setTime": "1 個月前",
    "star": 5
  },
  {
    "content": "自然農場，有許多可拍照的3D牆\n可拍美美的網美牆\n有空可以來逛逛",
    "name": "鍾淑芬",
    "setTime": "1 個月前",
    "star": 5
  },
  {
    "content": "一般般",
    "name": "陳耀輝",
    "setTime": "1 個月前",
    "star": 3
  },
  {
    "content": "門票200，不能全額折抵，只能折抵消費50，以不大的園區內不多的設施個人感覺不是很值得。\n餐點(火鍋)的CP值不高，可以用信用卡結帳，但門票跟購買禮品卻要用現金，在這個時代頗奇怪的。\n取名琉璃仙境，跟園區內的任何事物都搭不上任何關係，真是神奇了...",
    "name": "Simon Keng",
    "setTime": "1 個月前",
    "star": 2
  },
  {
    "content": "一個適合情侶拍照及觀賞動物以及讓小朋友遊玩放風的好去處。",
    "name": ",倫",
    "setTime": "1 個月前",
    "star": 5
  },
  {
    "content": "天竺鼠的叫聲很可愛\n來第二次 上次的動物 是 草尼馬跟小馬 可惜這次來沒有了 上次都沒來的及拍動物 動物都休息了 xD",
    "name": "兮兮",
    "setTime": "1 個月前",
    "star": 5
  },
  {
    "content": "美拍最佳景點、聚餐約會好所在、餐點下午茶美味👍👍",
    "name": "劉双惠",
    "setTime": "1 個月前",
    "star": 5
  },
  {
    "content": "風景美，拍照好景點，小火鍋，冰品都好吃，強力推薦，彰化好景點！",
    "name": "明祿黃",
    "setTime": "1 個月前",
    "star": 5
  },
  {
    "content": "原來員林有這麼美的地方啊~\n環境舒適、景色優美，超適合拍照打卡的....",
    "name": "吳雪菁",
    "setTime": "1 個月前",
    "star": 5
  },
  {
    "content": "風景美，氣氛佳，麻辣火鍋讚，\n美美照，拍好拍滿，打卡還送小禮物唷！",
    "name": "張彩綾",
    "setTime": "1 個月前",
    "star": 5
  },
  {
    "content": "好玩好玩很大很美適合家人一起來玩讚讚讚讚",
    "name": "許妙如",
    "setTime": "1 個月前",
    "star": 5
  },
  {
    "content": "很特別的香皂口味，很吸引人，也很舒服的觸感\n\n出遊來玩總是帶點紀念品回家",
    "name": "李宗憲",
    "setTime": "1 個月前",
    "star": 5
  },
  {
    "content": "園區很大很大！又漂亮又好玩！肥皂很香很香！讚讚！",
    "name": "辜莞婷",
    "setTime": "1 個月前",
    "star": 5
  },
  {
    "content": "適合親子遊玩的地方，園區還貼心準備雨傘，不管是遮雨或遮陽都很方便",
    "name": "阿佑嚴",
    "setTime": "1 個月前",
    "star": 5
  },
  {
    "content": "真的很適合來拍美美婚紗照的地方！！\n連廁所也很夢幻...超好拍吶~~\n婚攝聖地♥️♥️♥️！！",
    "name": "Wu Angela",
    "setTime": "1 個月前",
    "star": 5
  },
  {
    "content": "環境漂亮 很好拍照打卡的地方～\n彰化縣民入場還免費喔！",
    "name": "呂承哲",
    "setTime": "1 個月前",
    "star": 5
  },
  {
    "content": "",
    "name": "張世傑",
    "setTime": "1 個月前",
    "star": 4
  },
  {
    "content": "",
    "name": "藍是最溫暖的顏色",
    "setTime": "1 個月前",
    "star": 5
  },
  {
    "content": "餐點意外的好吃豐富，服務員服務非常親切，雖然場地不大",
    "name": "呂俐瑩",
    "setTime": "1 個月前",
    "star": 5
  },
  {
    "content": "農場餐點意外的豐富好吃，服務員們也非常親切！",
    "name": "Liying Lu",
    "setTime": "1 個月前",
    "star": 5
  },
  {
    "content": "在網上不經意看到，也不是假日來，不清楚假日人流狀況...\n個人感覺像在“住宅區”裏的“小綠地”\n地方不大，適合小家庭短時間休息散步/下午茶/簡易拍照取景/場地租賃辦理小規模聚會活動/購買香皂/精油產品與小物。\n\n有停車場/入園需購票，票劵可折抵園內消費/有提供傘遮陽/避雨\n洗手間/餐廳冷氣強頗優😆\n\n建議商家要定期環境維護，保持遊客觀感與品質。",
    "name": "林安然",
    "setTime": "1 個月前",
    "star": 3
  },
  {
    "content": "場景很漂亮，適合拍照。另外室外有草原草地可以讓小孩奔跑玩耍，還有滾球可以玩喔。讓大人小孩都放鬆的。想要拍美美的網美照可以來喔。親子也很適合，增加親子關係👍",
    "name": "Yi Wei",
    "setTime": "1 個月前",
    "star": 5
  },
  {
    "content": "真的像人間仙境一樣美倫美奐的，景點也很漂亮很適合網美拍照唷",
    "name": "鄭弘毅",
    "setTime": "1 個月前",
    "star": 5
  },
  {
    "content": "適合小朋友遊玩 有大大的草地 玩沙池 好吃的食物 美麗的拍照地點✌🏻✌🏻 …",
    "name": "Hsuan Tsai",
    "setTime": "1 個月前",
    "star": 5
  },
  {
    "content": "",
    "name": "江三榮",
    "setTime": "1 個月前",
    "star": 4
  },
  {
    "content": "很漂亮的地方",
    "name": "許馨文",
    "setTime": "1 個月前",
    "star": 5
  },
  {
    "content": "打卡五星送好禮 縣民還不用門票 太令人感動了",
    "name": "陳昕禾",
    "setTime": "1 個月前",
    "star": 5
  },
  {
    "content": "好玩 好拍",
    "name": "蘇麗珍",
    "setTime": "1 個月前",
    "star": 5
  },
  {
    "content": "好玩，好吃，適合闔家旅遊來訪",
    "name": "Eva chou",
    "setTime": "1 個月前",
    "star": 5
  },
  {
    "content": "門票200元可折抵50元，超適合拍照打卡。",
    "name": "Peter",
    "setTime": "1 個月前",
    "star": 3
  },
  {
    "content": "畫作美，建築物美",
    "name": "許金枝",
    "setTime": "1 個月前",
    "star": 4
  },
  {
    "content": "環境優美，適合全家人一起來走走",
    "name": "祖看陳",
    "setTime": "1 個月前",
    "star": 5
  },
  {
    "content": "風景很好拍小朋友來這裡更好玩火鍋吃到飽超讚的👏👏 …",
    "name": "李美惠",
    "setTime": "1 個月前",
    "star": 5
  },
  {
    "content": "服務好..又親切..餐點好吃…有好多可拍照..很適合朋友一起來。",
    "name": "余彥廷",
    "setTime": "1 個月前",
    "star": 5
  },
  {
    "content": "值得來，好停車，東西不錯吃，很好拍，裡面東西很好買。",
    "name": "楊小宛",
    "setTime": "1 個月前",
    "star": 5
  },
  {
    "content": "餐點變好吃了，非常可以來打卡，帶小孩來逛來玩沙很適合。",
    "name": "楊英琦",
    "setTime": "1 個月前",
    "star": 5
  },
  {
    "content": "各種香氛很棒棒 冷氣很強 下次還想來吃麻辣鍋，去隔壁蹭的咖哩鍋也好吃",
    "name": "蔡品柔",
    "setTime": "1 個月前",
    "star": 5
  },
  {
    "content": "建築物非常漂亮的地方，麻辣鍋很好吃，值得再次參訪.",
    "name": "陳小如",
    "setTime": "1 個月前",
    "star": 5
  },
  {
    "content": "麻辣鍋的湯底很好吃！麻辣鴨血和豆腐還能免費續，冷氣很強 夏天來很好w",
    "name": "蔡定軒",
    "setTime": "1 個月前",
    "star": 5
  },
  {
    "content": "好玩好逛的農場體驗！又有美食和商品可逛可買可拍照！真是一間二顧的好地方",
    "name": "蔡建暉",
    "setTime": "1 個月前",
    "star": 5
  },
  {
    "content": "整體來說，農場內乾淨整潔。\n適合小孩遊玩，大人可拍照\n天氣好很好拍\n廣場很大，小孩很好放電\n天氣炎熱，農場有提供遮陽傘，整個很貼心",
    "name": "冠賢呂",
    "setTime": "1 個月前",
    "star": 5
  },
  {
    "content": "餐點好吃，服務態度良好，適合全家一起來玩，琉璃仙境服務員超可愛唷～",
    "name": "黃鈺桂",
    "setTime": "1 個月前",
    "star": 5
  },
  {
    "content": "園區好好逛，風景超級美，照片很好拍，店員又美又可愛，值得一逛再逛…",
    "name": "Chiou Shin Huang",
    "setTime": "1 個月前",
    "star": 5
  },
  {
    "content": "非彰化縣民，大人一人200元，入內可折抵50元消費，可以玩的東西比較少，吃的種類也少，購物商店品項種類少(肥皂、精油這類的)，去的時候動物只看到兔子(可遠觀)，造景多，比較建議是專程來拍照的人比較適合，如果剛好是彰化縣民免門票來走走應該也是會覺得還不錯。",
    "name": "Ming Chen",
    "setTime": "1 個月前",
    "star": 4
  },
  {
    "content": "",
    "name": "ジェイミー竜",
    "setTime": "1 個月前",
    "star": 4
  },
  {
    "content": "環境很美，餐點也好吃，但唯一美中不足是下雨天☔️工作人員好辛苦！必須撐著雨傘，端著餐點來來去去，一手拿著餐點一手拿著雨傘，看他們鞋子都淋濕了！",
    "name": "張宜虹",
    "setTime": "1 個月前",
    "star": 4
  },
  {
    "content": "一個非常美麗的拍照地點",
    "name": "蔡可怡",
    "setTime": "1 個月前",
    "star": 5
  },
  {
    "content": "適合拍照，還有吃飯的地方",
    "name": "蔡可欣",
    "setTime": "1 個月前",
    "star": 5
  },
  {
    "content": "",
    "name": "Jian Bo",
    "setTime": "1 個月前",
    "star": 4
  },
  {
    "content": "非常適合全家人一起來\n園區服務人員解說親切",
    "name": "莊世安",
    "setTime": "1 個月前",
    "star": 5
  },
  {
    "content": "風景具有特色、用餐地方有水管屋很特別、有好吃的雪花冰，值得來走走逛逛。",
    "name": "詹秉豐",
    "setTime": "1 個月前",
    "star": 5
  },
  {
    "content": "風景優美,雨傘漂亮好用踩不斷、洗髮精好用、值得推薦.",
    "name": "詹建盈",
    "setTime": "1 個月前",
    "star": 5
  },
  {
    "content": "環境優美、適合網美來拍照、小孩戲水玩的很開心，也有沖洗換衣服的地方值得來玩玩。",
    "name": "黃律棉",
    "setTime": "1 個月前",
    "star": 5
  },
  {
    "content": "規劃的不錯",
    "name": "bruce Kam",
    "setTime": "1 個月前",
    "star": 5
  },
  {
    "content": "仙境～很好拍，天氣太好，不過有貼心可以借傘，聽說廁所裏有冷氣😄 …",
    "name": "陳依君",
    "setTime": "1 個月前",
    "star": 5
  },
  {
    "content": "熱銷第一名 便宜又好看",
    "name": "bill坤峰",
    "setTime": "1 個月前",
    "star": 5
  },
  {
    "content": "熱銷第一名\n便宜又好看\n服務人員和藹可親\n環境乾淨\n適合全家大小出遊",
    "name": "綉美",
    "setTime": "1 個月前",
    "star": 5
  },
  {
    "content": "梧鳳幼兒園的戶外教學帶小孩來走走，天氣晴朗，服務員服務超好！",
    "name": "邱宏展",
    "setTime": "1 個月前",
    "star": 5
  },
  {
    "content": "趁現在彰化縣民免門票，趕快帶小孩來走走，市集裡面的服務生很親切有禮貌～",
    "name": "于庭邱",
    "setTime": "1 個月前",
    "star": 5
  },
  {
    "content": "很棒又漂亮，服務又週到很新高興能來到這裡觀光",
    "name": "陳瀅溱",
    "setTime": "1 個月前",
    "star": 5
  },
  {
    "content": "這裡適合拍照打卡，他的餐也令人期待\n這裡香氛吊飾也很好買唷",
    "name": "黃思瑋",
    "setTime": "1 個月前",
    "star": 5
  },
  {
    "content": "好玩、有趣，適合遛小孩，而且園區很大，可以以好好逛逛，也有餐飲服務。讚！！",
    "name": "Chia-Jen Hu (HCJ)",
    "setTime": "1 個月前",
    "star": 5
  },
  {
    "content": "",
    "name": "張桂鵬（烏龍茶）",
    "setTime": "1 個月前",
    "star": 4
  },
  {
    "content": "",
    "name": "賴建瑋",
    "setTime": "1 個月前",
    "star": 5
  },
  {
    "content": "園區不大，藝術裝置已經可以看到歲月的痕跡，期待園方能夠重新粉刷。",
    "name": "黃柏仁",
    "setTime": "1 個月前",
    "star": 3
  },
  {
    "content": "這裡有的吃有的玩，是拍照的好地點，適合全家大小一同來遊玩喔！",
    "name": "tony tt",
    "setTime": "1 個月前",
    "star": 5
  },
  {
    "content": "這裡很適合拍網美照，適合全家大小一起散心，真的是斗六中的仙境～",
    "name": "Dana Sundeng",
    "setTime": "1 個月前",
    "star": 5
  },
  {
    "content": "價格有理，園區很大、很好逛，冷氣很涼，店員也很親切！",
    "name": "吳鳳如",
    "setTime": "1 個月前",
    "star": 5
  },
  {
    "content": "很棒很喜歡推薦來拍拍照片唷，服務也很不錯唷",
    "name": "米血《小精靈》",
    "setTime": "1 個月前",
    "star": 5
  },
  {
    "content": "服務態度很親切，市集區店員也都很熱心依喜好做介紹分享，環境舒適很適合全家大小一起來👍",
    "name": "Sing",
    "setTime": "1 個月前",
    "star": 5
  },
  {
    "content": "園區很美，導覽解說的很詳細，琉璃仙境休閒農場棒棒的呦～",
    "name": "陳金僑",
    "setTime": "1 個月前",
    "star": 5
  },
  {
    "content": "環境很棒很美",
    "name": "李慧貞",
    "setTime": "1 個月前",
    "star": 5
  },
  {
    "content": "好用的手工香皂，很好拍的網紅景點。好吃的美食",
    "name": "大吃貨",
    "setTime": "1 個月前",
    "star": 5
  },
  {
    "content": "風景優美很適合來這裡逛逛，市集小姐親切又可愛。\n可以來美拍唷！",
    "name": "呂妙真",
    "setTime": "1 個月前",
    "star": 5
  },
  {
    "content": "美美的好拍景點，還有香香的香皂專區..趕快來喔",
    "name": "Sandy Hsiao",
    "setTime": "1 個月前",
    "star": 5
  },
  {
    "content": "環境不錯，很漂亮，cp值很高，很好拍照，還有空地可以玩球。",
    "name": "劉函函",
    "setTime": "1 個月前",
    "star": 5
  },
  {
    "content": "園區處處都有提供陽傘很棒，好玩又好拍，很適合大人遛小孩放電。",
    "name": "劉珮玟",
    "setTime": "1 個月前",
    "star": 5
  },
  {
    "content": "很漂亮美麗的地方，婚紗攝影的最佳選擇，棒棒\n以後我女兒長大一定叫她來",
    "name": "吳盈壹",
    "setTime": "1 個月前",
    "star": 5
  },
  {
    "content": "這裡環境優美很舒服，拍照走走親子情侶時光很適合",
    "name": "孟林定洋",
    "setTime": "1 個月前",
    "star": 5
  },
  {
    "content": "環境優美，有很多可愛的小動物，非常適合全家大小一起來玩！大推特推",
    "name": "小雨",
    "setTime": "1 個月前",
    "star": 5
  },
  {
    "content": "與家人一同來走走玩玩，環境優美寬敞，氛圍舒適，很適合讓全家大小來玩！",
    "name": "畫魚",
    "setTime": "1 個月前",
    "star": 5
  },
  {
    "content": "咖哩鍋很香，微辣開胃。\n買了專用皂回去洗，很好溜小孩的地方。",
    "name": "賴玉旻",
    "setTime": "1 個月前",
    "star": 5
  },
  {
    "content": "剛好看到現居住的彰化縣民，ㄑ來琉璃仙鏡憑身份証明，即免門票入園區欣賞，真是太感謝，太好了",
    "name": "余景皓",
    "setTime": "1 個月前",
    "star": 5
  },
  {
    "content": "停車的位子非常大，有大小車的停車場，而且還有樹蔭，不會一上車就悶的受不了。",
    "name": "蕭玉展",
    "setTime": "1 個月前",
    "star": 4
  },
  {
    "content": "",
    "name": "劉仙台",
    "setTime": "1 個月前",
    "star": 5
  },
  {
    "content": "環境不錯 餐點優秀",
    "name": "Wei R",
    "setTime": "1 個月前",
    "star": 5
  },
  {
    "content": "",
    "name": "jacky chen",
    "setTime": "1 個月前",
    "star": 5
  },
  {
    "content": "",
    "name": "JohnCloud",
    "setTime": "1 個月前",
    "star": 5
  },
  {
    "content": "彰化縣民免費入場琉璃仙境 買了香氛吊飾感覺還不錯😌 …",
    "name": "小桓",
    "setTime": "1 個月前",
    "star": 5
  },
  {
    "content": "很精緻的景點，適合寫真拍照打卡。",
    "name": "William Wang",
    "setTime": "1 個月前",
    "star": 5
  },
  {
    "content": "裡面東西很漂亮，東西很好吃",
    "name": "林素卿",
    "setTime": "1 個月前",
    "star": 5
  },
  {
    "content": "琉璃藝術最美、琉璃藝術最用心服務最好、大家來走走",
    "name": "顏伯卿",
    "setTime": "1 個月前",
    "star": 5
  },
  {
    "content": "風景優美,服務熱情親切,美食棒,擂茶好喝,讚讚讚",
    "name": "戴語嫻",
    "setTime": "1 個月前",
    "star": 5
  },
  {
    "content": "琉璃仙境休閒農場超棒的網美拍照景點，拍好拍滿",
    "name": "戴娥",
    "setTime": "1 個月前",
    "star": 5
  },
  {
    "content": "好拍好逛",
    "name": "康育慈",
    "setTime": "1 個月前",
    "star": 4
  },
  {
    "content": "好拍，服務人員態度好，用餐環境不錯",
    "name": "簡于珊",
    "setTime": "1 個月前",
    "star": 5
  },
  {
    "content": "這裡好拍\n服務人員態度好\n用餐環境不錯\n餐點好吃",
    "name": "王雅琪",
    "setTime": "1 個月前",
    "star": 5
  },
  {
    "content": "環境很優美服務人員很好\n值得一直在來\n來到這裡來到不想回家\n餐點好吃",
    "name": "婷婷",
    "setTime": "1 個月前",
    "star": 5
  },
  {
    "content": "",
    "name": "吳明勳",
    "setTime": "1 個月前",
    "star": 4
  },
  {
    "content": "對輪椅族及老人很友善的景點~",
    "name": "張文",
    "setTime": "1 個月前",
    "star": 5
  },
  {
    "content": "",
    "name": "王子嘉（IWC789789）",
    "setTime": "1 個月前",
    "star": 5
  },
  {
    "content": "世外桃園美不勝收",
    "name": "江讚黨",
    "setTime": "1 個月前",
    "star": 5
  },
  {
    "content": "很漂亮，很適合親子遊玩",
    "name": "陳一火",
    "setTime": "1 個月前",
    "star": 5
  },
  {
    "content": "熊貓很可愛，這種地方很適合和家人一起來",
    "name": "陳品心",
    "setTime": "1 個月前",
    "star": 5
  },
  {
    "content": "裡面很漂亮，可以來參觀喔",
    "name": "陳怡君",
    "setTime": "1 個月前",
    "star": 5
  },
  {
    "content": "第一次來這邊，感覺還不錯，蠻推薦來走走",
    "name": "黃秋娥",
    "setTime": "1 個月前",
    "star": 5
  },
  {
    "content": "來琉璃仙境，很好拍照也很好聽玩，餐點好吃",
    "name": "ruby wen",
    "setTime": "1 個月前",
    "star": 5
  },
  {
    "content": "很多適合拍照的點，推薦來這裡拍照走走",
    "name": "Kelly wang",
    "setTime": "1 個月前",
    "star": 5
  },
  {
    "content": "很好玩又很特別",
    "name": "柯柯",
    "setTime": "1 個月前",
    "star": 5
  },
  {
    "content": "這裡很適合拍照打卡歡迎來玩",
    "name": "王淑珠",
    "setTime": "1 個月前",
    "star": 5
  },
  {
    "content": "琉璃仙境讚喔！",
    "name": "羅朝珠",
    "setTime": "1 個月前",
    "star": 5
  },
  {
    "content": "漂亮美麗的景點！讚喔！",
    "name": "劉夢琳",
    "setTime": "1 個月前",
    "star": 5
  },
  {
    "content": "適合網美拍照的景點",
    "name": "小惠蔡",
    "setTime": "1 個月前",
    "star": 5
  },
  {
    "content": "園區內建築唯美典雅，白色教堂營造出聖潔之風，可惜裡面只提供團膳，我們兩人無法進入。建議也能供散客在內用餐。而星座包廂只提供用餐時段進入，當天已客滿，於是只能等待到13:30選擇另一邊的餐廳。\n\n另有許多夢幻風格的壁畫，不同的角落藏著讓人驚喜的彩繪，令人目不暇給，很適合美拍。雖然園區不大，但精心維護，是值得推薦的彰化景點之一。",
    "name": "K L",
    "setTime": "1 個月前",
    "star": 4
  },
  {
    "content": "這裡景色宜人，景區造景好看出片，環境良好服務周到，貼心借傘服務，非常值得在週末來訪遊玩！",
    "name": "宇孜",
    "setTime": "1 個月前",
    "star": 5
  },
  {
    "content": "環境不錯，適合帶小孩來放電，玩沙、玩球跟泡腳，假日還有熊貓表演，很棒的地方。",
    "name": "劉莉美",
    "setTime": "1 個月前",
    "star": 5
  },
  {
    "content": "適合拍照好地方，假日來，剛好有熊貓表演，小孩玩到瘋，有泡腳池，水冰冰涼涼，好舒服。",
    "name": "Ying Liu",
    "setTime": "1 個月前",
    "star": 5
  },
  {
    "content": "神奇的琉璃仙境 不來不知道 一來嚇一跳 隨便拍隨便美耶 天熱還提供園區傘給遊客使用 真的是太貼心 超值！",
    "name": "小張",
    "setTime": "1 個月前",
    "star": 5
  },
  {
    "content": "沒去過",
    "name": "啊諾大人",
    "setTime": "1 個月前",
    "star": 5
  },
  {
    "content": "這裡拍照很漂亮，還有泡腳池跟小動物",
    "name": "張淑婷",
    "setTime": "1 個月前",
    "star": 5
  },
  {
    "content": "塑膠聯誼會剛好遇到暑假，就帶著小朋友們一起來走走",
    "name": "賴燦耀",
    "setTime": "1 個月前",
    "star": 5
  },
  {
    "content": "再次到訪琉璃仙境，很推薦來這裏拍照走走",
    "name": "芳秋張",
    "setTime": "1 個月前",
    "star": 5
  },
  {
    "content": "讚👍很美適合親子全家來玩～",
    "name": "周小瀚",
    "setTime": "1 個月前",
    "star": 5
  },
  {
    "content": "樂樂服務很好！一\n第一名，香皂很好洗很好用",
    "name": "王至芬",
    "setTime": "1 個月前",
    "star": 5
  },
  {
    "content": "這裡的風景太棒啦東西又好吃下次還要再來",
    "name": "陳金蓮",
    "setTime": "1 個月前",
    "star": 5
  },
  {
    "content": "琉璃仙境風景真美服務人員親切大方!",
    "name": "林紫鳳",
    "setTime": "1 個月前",
    "star": 5
  },
  {
    "content": "這裡風景優美適合來這裡拍照，服務很親切非常適合推薦來這裡",
    "name": "叢曼如",
    "setTime": "1 個月前",
    "star": 5
  },
  {
    "content": "可以下午茶，夏天傍晚一點再逛，大概4點半太陽慢慢小",
    "name": "邱小喬",
    "setTime": "1 個月前",
    "star": 5
  },
  {
    "content": "今天帶寶貝來這裡，非常適合親子旅遊的好地方，也很適合來這裡拍美美的網美拍照片回家",
    "name": "陳燕",
    "setTime": "1 個月前",
    "star": 5
  },
  {
    "content": "這個地方比較適合喜歡拍照的人，不管怎麼拍都很好看",
    "name": "黃馨瑩",
    "setTime": "1 個月前",
    "star": 5
  },
  {
    "content": "",
    "name": "Kevin Shih",
    "setTime": "1 個月前",
    "star": 5
  },
  {
    "content": "彰化縣民免費，帶小孩來遊玩！",
    "name": "賴依萱",
    "setTime": "1 個月前",
    "star": 5
  },
  {
    "content": "好漂亮的點啊 不管是哪邊都很好拍\n裡面也有餐廳跟禮品店可以吃喝跟買\n旁邊還有辛苦的街頭藝人在唱歌\n來這邊真的蠻放鬆的 大推！！！\n（門票是200元 可以折抵50消費喔）\n對了走之前還有兩隻熊貓🐼超可愛的啦\n\n———————————————————————\n整體環境：🌟🌟🌟🌟🌟\n服務品質：🌟🌟🌟🌟🌟\n餐點口味：🌟🌟🌟🌟🌟\n價格CP值：🌟🌟🌟🌟🌟\n整體評分：🌟🌟🌟🌟🌟\n✍️（1-2星較不推薦，3星普通，4-5推薦",
    "name": "mao jun",
    "setTime": "1 個月前",
    "star": 5
  },
  {
    "content": "風景美、咖喱鍋又好吃，到處都可以拍照👍🏻 …",
    "name": "Xinya Chen",
    "setTime": "1 個月前",
    "star": 5
  },
  {
    "content": "好吃、新奇、又好玩，拍照造型很美麗，火鍋吃到飽超級划算，遛小孩的好地方。",
    "name": "koy Lee",
    "setTime": "1 個月前",
    "star": 5
  },
  {
    "content": "園區蠻大的，也提供遮陽傘，小店的手工皂還不錯",
    "name": "missy chou",
    "setTime": "1 個月前",
    "star": 4
  },
  {
    "content": "園區精心的設計，每一處都是拍照的好景點",
    "name": "廖麗娟",
    "setTime": "1 個月前",
    "star": 5
  },
  {
    "content": "產品是天然原料置作氣味和質感都很好,很喜歡！",
    "name": "王武威",
    "setTime": "1 個月前",
    "star": 5
  },
  {
    "content": "彰化琉璃仙境~地方廣又美，是休閒旅遊ㄉ好所在",
    "name": "emily wu",
    "setTime": "1 個月前",
    "star": 5
  },
  {
    "content": "發鬆休閒的好地方",
    "name": "李曉玲",
    "setTime": "1 個月前",
    "star": 5
  },
  {
    "content": "",
    "name": "謝麗雲",
    "setTime": "1 個月前",
    "star": 4
  },
  {
    "content": "美美的",
    "name": "周凝願",
    "setTime": "1 個月前",
    "star": 5
  },
  {
    "content": "景觀美麗 服務品質佳 值得再來",
    "name": "ShuRu Huang",
    "setTime": "1 個月前",
    "star": 5
  },
  {
    "content": "超美。超大又好逛。服務也不錯喲❤️❤️\n紀念品區。很多可以買👍👍👍 …",
    "name": "吳芷菱",
    "setTime": "1 個月前",
    "star": 5
  },
  {
    "content": "七月開始彰化縣民免費入園\n打卡送小禮～～",
    "name": "劉瓊玟",
    "setTime": "1 個月前",
    "star": 5
  },
  {
    "content": "園區很大，有很特別的包箱餐廳，冰品好吃，還有駐唱歌手，很棒棒👍👍👍 …",
    "name": "Shirley",
    "setTime": "1 個月前",
    "star": 5
  },
  {
    "content": "",
    "name": "黃素真",
    "setTime": "1 個月前",
    "star": 4
  },
  {
    "content": "涼香膏很不錯！買三送一",
    "name": "Jerry",
    "setTime": "1 個月前",
    "star": 5
  },
  {
    "content": "好吃好玩擂茶好喝",
    "name": "Annie Tzou",
    "setTime": "1 個月前",
    "star": 5
  },
  {
    "content": "園區美侖美奐拍照的好地方",
    "name": "張瀅婕",
    "setTime": "1 個月前",
    "star": 5
  },
  {
    "content": "第一次來琉璃仙境真不錯",
    "name": "張秋月",
    "setTime": "1 個月前",
    "star": 5
  },
  {
    "content": "美麗的園區 冷氣很涼 乾凈清爽",
    "name": "梁wyoyen",
    "setTime": "1 個月前",
    "star": 5
  },
  {
    "content": "感覺這裡很漂亮！而且很好拍照！讓你擁有一雙翅膀！讚～～",
    "name": "陳翰毅",
    "setTime": "1 個月前",
    "star": 5
  },
  {
    "content": "超好拍！！！好多景可以發揮，建議一定要帶自拍棒。很適合情侶一起來拍照。",
    "name": "Ting Hui Lee",
    "setTime": "1 個月前",
    "star": 5
  },
  {
    "content": "非常漂亮的景點 搭配好吃的餐點 推薦大家來員林玩",
    "name": "偷逆",
    "setTime": "1 個月前",
    "star": 5
  },
  {
    "content": "琉璃仙境真宛如世外桃園\n園區服務小姐態度好氣質好。",
    "name": "林傑榮",
    "setTime": "1 個月前",
    "star": 5
  },
  {
    "content": "彰化員林好去處～很優美輕鬆的親子情侶家人的一日遊",
    "name": "蔡阿倫",
    "setTime": "1 個月前",
    "star": 5
  },
  {
    "content": "場地不錯，適合全家一起來遊玩順便拍照吃中餐",
    "name": "正港古早味",
    "setTime": "1 個月前",
    "star": 5
  },
  {
    "content": "",
    "name": "Huang Amy",
    "setTime": "1 個月前",
    "star": 5
  },
  {
    "content": "景觀漂亮美麗，餐點好吃、服務態度佳\n喜歡員工小美的服務態度，琉璃市集服務的妹妹態度也很好，下次會在光臨",
    "name": "黃浚家",
    "setTime": "1 個月前",
    "star": 5
  },
  {
    "content": "彰化線員林好去處\n很優美輕鬆的親子/情侶/家人的一日遊",
    "name": "粘小美",
    "setTime": "1 個月前",
    "star": 5
  },
  {
    "content": "非常適合全家來遊玩，門票200元可折抵50元，超適合拍照打卡。",
    "name": "025吳信賢",
    "setTime": "1 個月前",
    "star": 5
  },
  {
    "content": "景觀很美很漂亮，餐點好好吃重質重量，服務人員都很親切、講解都很仔細，下次會想在來哦",
    "name": "蔡嘉鳳",
    "setTime": "1 個月前",
    "star": 5
  },
  {
    "content": "好美的風景可以拍照🥳享用美味的料理吃到飽可以推薦的好地方👍",
    "name": "ChihWei Lin",
    "setTime": "1 個月前",
    "star": 5
  },
  {
    "content": "琉璃仙境好吃又好玩歡迎大家一起來",
    "name": "黃素碧",
    "setTime": "1 個月前",
    "star": 5
  },
  {
    "content": "琉璃仙境好吃又好玩風景優美歡迎大家一起來",
    "name": "Eagle Sky",
    "setTime": "1 個月前",
    "star": 5
  },
  {
    "content": "太漂亮了，很推薦大家來這裡走走拍照",
    "name": "盧梅蘭",
    "setTime": "1 個月前",
    "star": 5
  },
  {
    "content": "網美景點+1",
    "name": "王寶鳳",
    "setTime": "1 個月前",
    "star": 5
  },
  {
    "content": "琉璃仙境風景漂亮，好吃又好玩，好好拍。",
    "name": "Lin湘涵",
    "setTime": "1 個月前",
    "star": 5
  },
  {
    "content": "這是個好吃 好拍 好美的好地方\n很適合愛拍照的朋友來這邊 很棒的好地方！",
    "name": "陳美玲",
    "setTime": "1 個月前",
    "star": 5
  },
  {
    "content": "風景非常美拍照很美\n風景優美適合帶小孩來放電",
    "name": "黃榆絜",
    "setTime": "1 個月前",
    "star": 5
  },
  {
    "content": "美麗仙境一樣的環境值得一遊.在夏日炎炎的季節也可以讓人很舒服😌 …",
    "name": "陳麗雪",
    "setTime": "1 個月前",
    "star": 5
  },
  {
    "content": "這裡風景很漂亮很適合來拍照，推薦來這裡逛逛",
    "name": "張玉玫",
    "setTime": "1 個月前",
    "star": 5
  },
  {
    "content": "",
    "name": "詹小峰",
    "setTime": "2 個月前",
    "star": 4
  },
  {
    "content": "網紅拍照點",
    "name": "林麗月",
    "setTime": "2 個月前",
    "star": 5
  },
  {
    "content": "",
    "name": "黃秋蘭",
    "setTime": "2 個月前",
    "star": 5
  },
  {
    "content": "",
    "name": "蔡玉娟",
    "setTime": "2 個月前",
    "star": 5
  },
  {
    "content": "在此一遊很漂亮很漂亮",
    "name": "may wang",
    "setTime": "2 個月前",
    "star": 5
  },
  {
    "content": "",
    "name": "yue yue",
    "setTime": "2 個月前",
    "star": 5
  },
  {
    "content": "拍婚紗的好去處， 網美打卡的好景點",
    "name": "Jessie Yang",
    "setTime": "2 個月前",
    "star": 4
  },
  {
    "content": "很美很漂亮的地方\n超適合假日來走走的\n讚讚👍 …",
    "name": "周孟儒",
    "setTime": "2 個月前",
    "star": 5
  },
  {
    "content": "非常棒的景點 可以吃冰\n還可以吃火鍋 下雨天還可以提供雨傘",
    "name": "呂嘉樺",
    "setTime": "2 個月前",
    "star": 5
  },
  {
    "content": "網美勝地，拍照景點很多 可以逛\n累了可以到餐廳吃火鍋 ，還有小朋友的兒童餐 。",
    "name": "簡彤彤",
    "setTime": "2 個月前",
    "star": 5
  },
  {
    "content": "餐點很好吃，服務人員很親切，風景優美～是適合約會拍照的好景點",
    "name": "Lin小靜",
    "setTime": "2 個月前",
    "star": 5
  },
  {
    "content": "環境很舒適",
    "name": "米妮",
    "setTime": "2 個月前",
    "star": 5
  },
  {
    "content": "餐廳要先預訂才能用餐",
    "name": "99 ysammi",
    "setTime": "2 個月前",
    "star": 5
  },
  {
    "content": "很舒服，很美麗、火鍋好吃\n水管屋很美",
    "name": "陳惠雯",
    "setTime": "2 個月前",
    "star": 5
  },
  {
    "content": "",
    "name": "陳雅娜",
    "setTime": "2 個月前",
    "star": 5
  },
  {
    "content": "網美景點～拍照好好拍！門票200/人 送100折價卷裡面消費可以折抵",
    "name": "Jason Hu",
    "setTime": "2 個月前",
    "star": 5
  },
  {
    "content": "超美網美聖地！購買精油膏服務人員耐心介紹和幫忙試按推薦超棒！",
    "name": "ASSY J",
    "setTime": "2 個月前",
    "star": 5
  },
  {
    "content": "這是個好吃 好拍 好美的好地方\n很適合愛拍照的朋友來這邊 很棒的好地方！\n我跟葳都很愛",
    "name": "Emily Chung",
    "setTime": "2 個月前",
    "star": 5
  },
  {
    "content": "香氛吊飾很厲害 有柑橘的芳香味\n很適合我在包包裡面 聞起來很清爽舒適",
    "name": "Ben",
    "setTime": "2 個月前",
    "star": 5
  },
  {
    "content": "超級好拍",
    "name": "黃俐瑄",
    "setTime": "2 個月前",
    "star": 5
  },
  {
    "content": "還不錯👍 東西有點少",
    "name": "YT翼神",
    "setTime": "2 個月前",
    "star": 5
  },
  {
    "content": "園區大又漂亮，帶小孩放風、吃飯、拍照的好地方，門票有抵一半消費",
    "name": "黃榮宗",
    "setTime": "2 個月前",
    "star": 5
  },
  {
    "content": "超級漂亮的地方很好玩很好拍照小孩超級喜歡",
    "name": "Fion Wang",
    "setTime": "2 個月前",
    "star": 5
  },
  {
    "content": "風景漂亮\n好拍照\n賣場冷氣涼爽\n東西好買",
    "name": "黃卓雄",
    "setTime": "2 個月前",
    "star": 5
  },
  {
    "content": "這隻灰色的兔子感覺奄奄一息了,希望能更用心照顧這些寵物",
    "name": "13",
    "setTime": "2 個月前",
    "star": 2
  },
  {
    "content": "拍照好地方",
    "name": "洪玲珠",
    "setTime": "2 個月前",
    "star": 5
  },
  {
    "content": "溜小孩的地方",
    "name": "Eddy Lin",
    "setTime": "2 個月前",
    "star": 5
  },
  {
    "content": "網美拍照的好景點，還有冰涼的泡腳池，門票可抵消費....",
    "name": "蔡珮瑜",
    "setTime": "2 個月前",
    "star": 5
  },
  {
    "content": "👍👍👍 …",
    "name": "賴韋嘉",
    "setTime": "2 個月前",
    "star": 5
  },
  {
    "content": "很棒的地方 東西也好吃",
    "name": "黃品慈",
    "setTime": "2 個月前",
    "star": 5
  },
  {
    "content": "服務佳！",
    "name": "Joan Lin",
    "setTime": "2 個月前",
    "star": 5
  },
  {
    "content": "超讚的～～很友善～～",
    "name": "UL AZ",
    "setTime": "2 個月前",
    "star": 5
  },
  {
    "content": "讚",
    "name": "陳婕翎",
    "setTime": "2 個月前",
    "star": 5
  },
  {
    "content": "超讚",
    "name": "郭舒婷",
    "setTime": "2 個月前",
    "star": 5
  },
  {
    "content": "讚",
    "name": "李麗花",
    "setTime": "2 個月前",
    "star": 4
  },
  {
    "content": "超棒的",
    "name": "吳秀萍",
    "setTime": "2 個月前",
    "star": 5
  },
  {
    "content": "讚👍 …",
    "name": "林春鳳",
    "setTime": "2 個月前",
    "star": 5
  },
  {
    "content": "棒",
    "name": "李貴蕉",
    "setTime": "2 個月前",
    "star": 4
  },
  {
    "content": "/\n\n非常棒",
    "name": "藍文龍",
    "setTime": "2 個月前",
    "star": 5
  },
  {
    "content": "好棒👍 …",
    "name": "陳庭庭",
    "setTime": "2 個月前",
    "star": 5
  },
  {
    "content": "好好看",
    "name": "林國陽",
    "setTime": "2 個月前",
    "star": 4
  },
  {
    "content": "環境優美",
    "name": "惠華",
    "setTime": "2 個月前",
    "star": 5
  },
  {
    "content": "非常棒",
    "name": "黃阿緞",
    "setTime": "2 個月前",
    "star": 5
  },
  {
    "content": "非常棒",
    "name": "李玉華",
    "setTime": "2 個月前",
    "star": 5
  },
  {
    "content": "好玩好好拍",
    "name": "唐欣宏",
    "setTime": "2 個月前",
    "star": 5
  },
  {
    "content": "讚",
    "name": "諠諠",
    "setTime": "2 個月前",
    "star": 5
  },
  {
    "content": "大推",
    "name": "劉琴",
    "setTime": "2 個月前",
    "star": 5
  },
  {
    "content": "好開心員林也有適合大人小朋友遊樂地方。很棒欸～大推",
    "name": "鈺小鈺",
    "setTime": "2 個月前",
    "star": 5
  },
  {
    "content": "這裡很漂亮 讚啦",
    "name": "liu Alex",
    "setTime": "2 個月前",
    "star": 5
  },
  {
    "content": "環境很U質 很漂亮",
    "name": "Jackie Liu",
    "setTime": "2 個月前",
    "star": 5
  },
  {
    "content": "環境乾淨，服務好",
    "name": "梁冬冬",
    "setTime": "2 個月前",
    "star": 5
  },
  {
    "content": "迎賓客家雷茶小點心\n中午吃了自助吃到飽小火鍋\n還試用6種不同味道肥皂\n愛上了檜木味道\n還帶回好人緣桃花\n看到了小香豬\n天氣熱 烏梅汁帶一瓶\n順便聽聽美妹唱歌雙人組合",
    "name": "Anita Liu",
    "setTime": "2 個月前",
    "star": 5
  },
  {
    "content": "環境很大很漂亮，非常好拍照，禮品店的好多東西都很特別，肥皂、香氛、護手霜都很香👍👍👍 …",
    "name": "黃雅雅",
    "setTime": "2 個月前",
    "star": 5
  },
  {
    "content": "場地很大很好逛 也很好拍照📷 擂茶 香氛吊飾都很讚👍 …",
    "name": "陳柏全",
    "setTime": "2 個月前",
    "star": 5
  },
  {
    "content": "火鍋很好吃～麻辣鍋底香氣十足\n很適合拍照～",
    "name": "林美汝",
    "setTime": "2 個月前",
    "star": 5
  },
  {
    "content": "風景優美，服務態度佳",
    "name": "鄭小英",
    "setTime": "2 個月前",
    "star": 5
  },
  {
    "content": "這裡很漂亮小姐服務很好，拍照好景點",
    "name": "簡簡政峰",
    "setTime": "2 個月前",
    "star": 5
  },
  {
    "content": "風景漂亮導覧小姐很好東西優惠",
    "name": "孫淑珍",
    "setTime": "2 個月前",
    "star": 5
  },
  {
    "content": "風景美，會多多支持喔",
    "name": "曹欣齊",
    "setTime": "2 個月前",
    "star": 5
  },
  {
    "content": "每個地方都是拍照景點，讓人流連忘返！下次還想再來",
    "name": "田碧燕",
    "setTime": "2 個月前",
    "star": 5
  },
  {
    "content": "風景超美啊！美美的自己！開心啊！",
    "name": "Jenny Lun",
    "setTime": "2 個月前",
    "star": 5
  },
  {
    "content": "",
    "name": "曾嘉文",
    "setTime": "2 個月前",
    "star": 3
  },
  {
    "content": "帶一家老小來放電的好處所⁎⁍̴̛ᴗ⁍̴̛⁎\n剛好天氣又很舒服",
    "name": "Ming",
    "setTime": "2 個月前",
    "star": 5
  },
  {
    "content": "很適合帶小朋友來吃飯逛街的農場！\n環境非常舒服😌 …",
    "name": "儒林幼兒園洪秀珠",
    "setTime": "2 個月前",
    "star": 5
  },
  {
    "content": "員工旅遊第一次來\n真的是拍照的好地方\n這裡很好拍唷",
    "name": "郭冰冰",
    "setTime": "2 個月前",
    "star": 5
  },
  {
    "content": "網美景點 拍照的好地方  大人小孩都喜歡 有好吃的又好玩",
    "name": "葉佳珍",
    "setTime": "2 個月前",
    "star": 5
  },
  {
    "content": "雖然夏天很熱！造景美\n很適合拍網美照！\n推薦情侶家人來",
    "name": "糖糖黃",
    "setTime": "2 個月前",
    "star": 5
  },
  {
    "content": "一個非常適合小朋友，情侶檔一起來的地方，很建議大家來玩，有歌手駐唱，有冷可以吃，浪漫",
    "name": "陳崇賢",
    "setTime": "2 個月前",
    "star": 5
  },
  {
    "content": "風景很美但飲料不推 奶茶一杯70喝起來根本是奶茶粉下去沖泡 這價格該有的品質卻沒有⋯甜的要命有夠難喝",
    "name": "羅子昀",
    "setTime": "2 個月前",
    "star": 1
  },
  {
    "content": "很美很棒\n心態不一樣 眼界就不一樣\n看到的世界自然就不同\n去靠近正能量的人\n才能收穫人生中的快樂與美好❤️",
    "name": "塗婉菁",
    "setTime": "2 個月前",
    "star": 5
  },
  {
    "content": "很適合小朋友玩耍放電的好地方！\n\n環境很棒 服務優質 很滿意 裝潢很棒",
    "name": "曹佩祺",
    "setTime": "2 個月前",
    "star": 5
  },
  {
    "content": "香氛涼香膏。味道好聞 又清爽\n天氣熱熱好適合擦ㄧ擦",
    "name": "游秀春",
    "setTime": "2 個月前",
    "star": 5
  },
  {
    "content": "很讚，很美，很漂亮，很好拍照，東西很好吃的地方，讚讚讚！",
    "name": "蔡惠美",
    "setTime": "2 個月前",
    "star": 5
  },
  {
    "content": "琉璃仙境風景非常漂亮，歡迎大家有空來坐坐歐。",
    "name": "蔡淑真",
    "setTime": "2 個月前",
    "star": 5
  },
  {
    "content": "琉璃仙境20230618旅遊，天氣好，風景很美，打卡活動很好",
    "name": "viviss64 LU",
    "setTime": "2 個月前",
    "star": 5
  },
  {
    "content": "很漂亮，很好拍照！很適合家庭一起玩樂出遊！火鍋吃到飽！讚讚讚👍 …",
    "name": "張硯婷",
    "setTime": "2 個月前",
    "star": 5
  },
  {
    "content": "",
    "name": "李秋香",
    "setTime": "2 個月前",
    "star": 5
  },
  {
    "content": "環境優美，綠化森林美倫美煥，餐點還不錯哦！！！讚喔！！！",
    "name": "黃詩音",
    "setTime": "2 個月前",
    "star": 5
  },
  {
    "content": "讚",
    "name": "許維卿",
    "setTime": "2 個月前",
    "star": 4
  },
  {
    "content": "這裡很好拍照，園區裡的服務人員服務很好，東西也不錯吃：）",
    "name": "米小恩",
    "setTime": "2 個月前",
    "star": 5
  },
  {
    "content": "東西好吃，舒適放鬆的地點，藏身於員林的巷弄間，很值得一來",
    "name": "蕭揚哲",
    "setTime": "2 個月前",
    "star": 5
  },
  {
    "content": "環境用心維護❤️\n服務人員很用心❤️",
    "name": "陳淑美",
    "setTime": "2 個月前",
    "star": 5
  },
  {
    "content": "外場服務人員都很好很棒！",
    "name": "life new",
    "setTime": "2 個月前",
    "star": 5
  },
  {
    "content": "東西好吃😋外場服務人員很細心親切❤️ …",
    "name": "劉瑜妃",
    "setTime": "2 個月前",
    "star": 5
  },
  {
    "content": "風景好、氣氛佳、食物鮮美\n適合全家出遊、雙人約會、單人沉浸式體驗",
    "name": "Hsuan Hsieh",
    "setTime": "2 個月前",
    "star": 5
  },
  {
    "content": "琉璃仙境好吃又好玩\n市集好好買 推薦😚🤗 …",
    "name": "蔡春香",
    "setTime": "2 個月前",
    "star": 5
  },
  {
    "content": "市集好好買\n琉璃手環好精緻\n香皂、精油、香氛吊飾天然好聞\n五🌟推薦✨😚😚 …",
    "name": "u liu",
    "setTime": "2 個月前",
    "star": 5
  },
  {
    "content": "來到童話故事世界裡..好多美麗的場景..好棒好美😍 …",
    "name": "廖芝儀",
    "setTime": "2 個月前",
    "star": 5
  },
  {
    "content": "",
    "name": "陳俊誠",
    "setTime": "2 個月前",
    "star": 4
  },
  {
    "content": "園區有12星座的包廂 可以用餐\n尤其是咖哩鍋好吃 不會太辣\n也有許多商品如肥皂、香氛吊飾可以購買\n適合家人一起來旅遊👍 …",
    "name": "莊峻誠",
    "setTime": "2 個月前",
    "star": 5
  },
  {
    "content": "好漂亮，琉璃仙境真美，漂亮好玩",
    "name": "王雅娟",
    "setTime": "2 個月前",
    "star": 5
  },
  {
    "content": "好美，好光景，琉璃仙境好玩",
    "name": "賴寵文",
    "setTime": "2 個月前",
    "star": 5
  },
  {
    "content": "琉璃仙境，第一次造訪，值得一遊",
    "name": "布袋",
    "setTime": "2 個月前",
    "star": 5
  },
  {
    "content": "琉璃仙境很夢幻拍照的好地方，婚紗拍照攝影都很不錯",
    "name": "York宥均",
    "setTime": "2 個月前",
    "star": 5
  },
  {
    "content": "服務人員親切，場景很美，值得推薦給大家去玩！",
    "name": "鄭恆順",
    "setTime": "2 個月前",
    "star": 5
  },
  {
    "content": "第一次來這裡裡面的服務人員超級可愛又美麗服務又超好大家快來玩哦",
    "name": "蘇惠珠",
    "setTime": "2 個月前",
    "star": 5
  },
  {
    "content": "服務人員親切，場景很美，很值得推薦給大家來玩！",
    "name": "平平楊",
    "setTime": "2 個月前",
    "star": 5
  },
  {
    "content": "",
    "name": "心念",
    "setTime": "2 個月前",
    "star": 4
  },
  {
    "content": "很不錯的拍照景點\n值得一遊👍 …",
    "name": "王艾薇",
    "setTime": "2 個月前",
    "star": 5
  },
  {
    "content": "今天禮拜六來到彰化琉璃仙境玩真開心",
    "name": "Lin Wu",
    "setTime": "2 個月前",
    "star": 5
  },
  {
    "content": "我老公冠融很白痴～一直說老婆，她這邊的育嬰室好高級！有冷氣欸！\n環境很棒、舒服，親子放鬆遊玩的好地方！",
    "name": "Wang Mia",
    "setTime": "2 個月前",
    "star": 5
  },
  {
    "content": "琉璃仙境休閒農場真漂亮拍照好景點，餐點吃到飽真滿意",
    "name": "徐玉嬌",
    "setTime": "2 個月前",
    "star": 5
  },
  {
    "content": "非常棒的玻璃仙境休閒農場非常適合大大小小的來玩",
    "name": "紗紗呂",
    "setTime": "2 個月前",
    "star": 5
  },
  {
    "content": "風景怡人適合年輕族群一探究竟\n好玩好看好吃都有…",
    "name": "羅德忠",
    "setTime": "2 個月前",
    "star": 5
  },
  {
    "content": "漂亮景點。拍照好地方。火鍋好吃。值得再來。推薦好友一遊。",
    "name": "蔣美",
    "setTime": "2 個月前",
    "star": 5
  },
  {
    "content": "唉琉璃仙境是個婚紗拍攝好地點也是環境優美好拍的地方",
    "name": "林玉妃",
    "setTime": "2 個月前",
    "star": 5
  },
  {
    "content": "第一次來參訪，氣氛非常好自助式火鍋超好吃，還有薩克斯風表演，值得推薦",
    "name": "廖宸育",
    "setTime": "2 個月前",
    "star": 5
  },
  {
    "content": "琉璃仙境休閒農場非常的棒，有空可以來拍照打卡。",
    "name": "姜禮炳",
    "setTime": "2 個月前",
    "star": 5
  },
  {
    "content": "風景美東西好吃值得再來教堂之造景漂亮",
    "name": "李彭雪華",
    "setTime": "2 個月前",
    "star": 5
  },
  {
    "content": "好玩，漂亮，新奇，午餐好好吃，好棒棒👌👌 …",
    "name": "彭春菊",
    "setTime": "2 個月前",
    "star": 5
  },
  {
    "content": "琉璃仙境不錯、好玩，好吃、有趣，快樂，讚、讚",
    "name": "王進富",
    "setTime": "2 個月前",
    "star": 5
  },
  {
    "content": "琉璃仙境好地方風景美,教堂漂亮",
    "name": "林阿忠",
    "setTime": "2 個月前",
    "star": 5
  },
  {
    "content": "非常好玩，好棒👍👍👍漂亮，新鮮美麗，午餐好吃 …",
    "name": "葉世明",
    "setTime": "2 個月前",
    "star": 5
  },
  {
    "content": "很棒，可放鬆心情，很多點好拍",
    "name": "邱雲媛",
    "setTime": "2 個月前",
    "star": 5
  },
  {
    "content": "琉璃仙境拍照好美，適合大家一起來玩樂！火鍋吃到飽讚👍 …",
    "name": "余宣穎",
    "setTime": "2 個月前",
    "star": 5
  },
  {
    "content": "琉璃仙境風景美很值得一遊拍照打卡超優新人拍婚照第一選擇",
    "name": "鍾訪錢",
    "setTime": "2 個月前",
    "star": 5
  },
  {
    "content": "五星好評換禮物 大家快來換喔 網美景點拍照的好地方讚讚讚",
    "name": "汪信在",
    "setTime": "2 個月前",
    "star": 5
  },
  {
    "content": "琉璃仙境很讚喔！很好拍照！適合家庭一起玩樂！",
    "name": "余宣穎",
    "setTime": "2 個月前",
    "star": 5
  },
  {
    "content": "非常漂亮的地方快來買東西拍美照吃美食讚讚讚",
    "name": "shou-huang li",
    "setTime": "2 個月前",
    "star": 5
  },
  {
    "content": "非常好的地方 工作人員都很熱心 可以拍很多王美照喔",
    "name": "康月宏",
    "setTime": "2 個月前",
    "star": 5
  },
  {
    "content": "環境好東西好吃歡迎大家一起來吃謝謝",
    "name": "許金子",
    "setTime": "2 個月前",
    "star": 5
  },
  {
    "content": "環境優美，大人小孩都適合\n拍照，東西好吃，歡迎大家一起來",
    "name": "童佳儀",
    "setTime": "2 個月前",
    "star": 5
  },
  {
    "content": "環境超棒 火鍋超好吃 很推咖哩鍋！肉很棒 服務人員都很好 打卡景點超多 還有可愛的小鹿斑比！大家一定要來看看",
    "name": "許維翔",
    "setTime": "2 個月前",
    "star": 5
  },
  {
    "content": "讚啦非常好的地方，漂亮的網美景點快來拍照玩一玩",
    "name": "Tseng Lin",
    "setTime": "2 個月前",
    "star": 5
  },
  {
    "content": "很好玩，很漂亮啊！還非常好拍照！火鍋吃到飽！讚👍 …",
    "name": "Chen Yo",
    "setTime": "2 個月前",
    "star": 5
  },
  {
    "content": "琉璃仙境庭園造景，美景盡收眼底，殺底片好地方。",
    "name": "Ok Ok",
    "setTime": "2 個月前",
    "star": 5
  },
  {
    "content": "臭臭的",
    "name": "徐志摩",
    "setTime": "2 個月前",
    "star": 1
  },
  {
    "content": "裡面的服務人員態度都很好 園區也很漂亮\n服務人員都是俊男美女",
    "name": "朱翊睿",
    "setTime": "2 個月前",
    "star": 5
  },
  {
    "content": "",
    "name": "Wenchi Chen",
    "setTime": "2 個月前",
    "star": 3
  },
  {
    "content": "",
    "name": "咩凝",
    "setTime": "2 個月前",
    "star": 5
  },
  {
    "content": "園區裡面很漂亮 星座餐廳的咖喱湯頭很香很入味 裡面有一個西瓜頭的男生服務非常好長得很帥",
    "name": "王立霆",
    "setTime": "3 個月前",
    "star": 5
  },
  {
    "content": "很棒的聚餐地點 環境很棒 服務優質 每個人都很滿意 裝潢很棒 晚上來別有一番風味!",
    "name": "蔡大全",
    "setTime": "3 個月前",
    "star": 5
  },
  {
    "content": "環境超棒 火鍋超好吃 很推咖哩鍋！肉很棒 服務人員都很好 打卡景點超多 還有可愛的小鹿斑比！大家一定要來看看",
    "name": "蔡喻丞",
    "setTime": "3 個月前",
    "star": 5
  },
  {
    "content": "",
    "name": "朱曉楓",
    "setTime": "3 個月前",
    "star": 5
  },
  {
    "content": "",
    "name": "丁明鳳",
    "setTime": "3 個月前",
    "star": 4
  },
  {
    "content": "",
    "name": "美顏技術科謝宜珍",
    "setTime": "3 個月前",
    "star": 5
  },
  {
    "content": "",
    "name": "王堉維",
    "setTime": "3 個月前",
    "star": 5
  },
  {
    "content": "很漂亮、是網美拍照的地點，服務也很好，值得遊玩的地方",
    "name": "張凱玲",
    "setTime": "3 個月前",
    "star": 5
  },
  {
    "content": "",
    "name": "維維WeiWei",
    "setTime": "3 個月前",
    "star": 5
  },
  {
    "content": "適合親子活動的地方\n\n餐點衛生，服務親切",
    "name": "謝佩芬",
    "setTime": "3 個月前",
    "star": 5
  },
  {
    "content": "很好拍照的地方，來到這邊很像世外桃源，覺得很放鬆，非常推薦大家前來遊玩",
    "name": "YoChen Lai",
    "setTime": "3 個月前",
    "star": 5
  },
  {
    "content": "咖哩鍋很好吃，裡面的協理很nice",
    "name": "賴宥辰",
    "setTime": "3 個月前",
    "star": 5
  },
  {
    "content": "",
    "name": "陳小蓁",
    "setTime": "3 個月前",
    "star": 5
  }
]