[
  {
    "content": "",
    "name": "july20211",
    "setTime": "4 週前",
    "star": 1
  },
  {
    "content": "日式瓦屋懷舊風情",
    "name": "tsai rong yaw",
    "setTime": "2 個月前",
    "star": 5
  },
  {
    "content": "關閉",
    "name": "賴民雄",
    "setTime": "2 年前",
    "star": 3
  },
  {
    "content": "",
    "name": "黃登宇",
    "setTime": "2 年前",
    "star": 5
  },
  {
    "content": "寧靜小巷的老房子，很有自己的小世界的氛圍，結合花蓮高中的校歌的老故事，適合拍照",
    "name": "look yang",
    "setTime": "2 年前",
    "star": 5
  },
  {
    "content": "郭老師很多音樂著作, 音樂文化館很容易可以找的到。很有紀念性的地方。",
    "name": "menghua yao",
    "setTime": "2 年前",
    "star": 4
  },
  {
    "content": "美妙而難忘的氛圍",
    "name": "連秀敏",
    "setTime": "2 年前",
    "star": 4
  },
  {
    "content": "",
    "name": "洪錫璿",
    "setTime": "2 年前",
    "star": 5
  },
  {
    "content": "充滿歷史感的地點，根據在這裡服務的志工阿姨所說，好像有要賣食物。",
    "name": "旻翰",
    "setTime": "2 年前",
    "star": 4
  },
  {
    "content": "",
    "name": "鄭曉風",
    "setTime": "2 年前",
    "star": 3
  },
  {
    "content": "內容有點少，日式建築拍照取景還不錯。",
    "name": "老楊",
    "setTime": "2 年前",
    "star": 3
  },
  {
    "content": "",
    "name": "ChenSW James",
    "setTime": "2 年前",
    "star": 3
  },
  {
    "content": "座落於花蓮高中對面，環境清幽",
    "name": "楊國吉",
    "setTime": "2 年前",
    "star": 4
  },
  {
    "content": "沒有什麼",
    "name": "joe chen",
    "setTime": "2 年前",
    "star": 1
  },
  {
    "content": "懷舊靜謐的境地",
    "name": "Grace Shih",
    "setTime": "2 年前",
    "star": 5
  },
  {
    "content": "民防是國防的基礎\n幾個斑駁的痕跡很懷舊",
    "name": "jinn flower",
    "setTime": "2 年前",
    "star": 5
  },
  {
    "content": "很棒的地方\n難忘的人\n優美的歌聲...\n度過一個美好的夜晚！",
    "name": "劉承文",
    "setTime": "2 年前",
    "star": 4
  },
  {
    "content": "整體而言，該區域維護的算不錯，活動少了些，多些活動，才能活絡古宅的美。",
    "name": "葉小熊",
    "setTime": "2 年前",
    "star": 3
  },
  {
    "content": "不錯,很靜謐的一個地方。保留下了日式風格特色",
    "name": "卡茲瑩瑩",
    "setTime": "2 年前",
    "star": 4
  },
  {
    "content": "",
    "name": "林佩蓉",
    "setTime": "2 年前",
    "star": 5
  },
  {
    "content": "很多童書，是個適合帶孩子去的親子友善文藝空間",
    "name": "李陳太太",
    "setTime": "2 年前",
    "star": 5
  },
  {
    "content": "古色古香的老建築",
    "name": "李志忠",
    "setTime": "2 年前",
    "star": 5
  },
  {
    "content": "古色古香的建築物",
    "name": "Ming Li",
    "setTime": "2 年前",
    "star": 5
  },
  {
    "content": "舊了一些，但別有一番風味",
    "name": "林政維（維維）",
    "setTime": "2 年前",
    "star": 4
  },
  {
    "content": "",
    "name": "jerry1844李凱霖",
    "setTime": "2 年前",
    "star": 5
  },
  {
    "content": "應該是9點半開始才對 負責管理的志工人都很好 因為一連四棟都是 不確定能不能進去可以去究巷咖啡問一下 那裡還有很多二手繪本可以買 真的很佩服郭老師對音樂及教育的熱忱",
    "name": "徐志宗",
    "setTime": "2 年前",
    "star": 5
  },
  {
    "content": "",
    "name": "Chenghen Yang",
    "setTime": "3 年前",
    "star": 4
  },
  {
    "content": "很適合親子來 ，有童書給孩子看！",
    "name": "Daphne Liu",
    "setTime": "3 年前",
    "star": 4
  },
  {
    "content": "",
    "name": "楊承閔",
    "setTime": "3 年前",
    "star": 5
  },
  {
    "content": "",
    "name": "姚璋",
    "setTime": "3 年前",
    "star": 5
  },
  {
    "content": "值得參觀的好地方，了解郭子究老師對音樂的熱情，在窮鄉僻壤的地方培育許多學生，真不簡單。",
    "name": "joan chang",
    "setTime": "3 年前",
    "star": 4
  },
  {
    "content": "認真的人最美麗…",
    "name": "Mars Du",
    "setTime": "3 年前",
    "star": 5
  },
  {
    "content": "",
    "name": "黃清照",
    "setTime": "3 年前",
    "star": 5
  },
  {
    "content": "",
    "name": "林東昱",
    "setTime": "3 年前",
    "star": 4
  },
  {
    "content": "",
    "name": "黃承雄",
    "setTime": "3 年前",
    "star": 5
  },
  {
    "content": "",
    "name": "Tony cho",
    "setTime": "3 年前",
    "star": 5
  },
  {
    "content": "花蓮合唱團團練",
    "name": "楊安娜",
    "setTime": "3 年前",
    "star": 5
  },
  {
    "content": "應有盡有，約會或是親子同樂的好地方！",
    "name": "張奕文",
    "setTime": "3 年前",
    "star": 5
  },
  {
    "content": "每星期日晚此合唱團的團練",
    "name": "黃黎明",
    "setTime": "3 年前",
    "star": 5
  },
  {
    "content": "環境優雅、適合小型音樂會、有一台河合平台鋼琴、音響設備及效果皆佳",
    "name": "Judy Hung",
    "setTime": "3 年前",
    "star": 5
  },
  {
    "content": "",
    "name": "minyu Leo",
    "setTime": "3 年前",
    "star": 5
  },
  {
    "content": "",
    "name": "Timo Huang",
    "setTime": "3 年前",
    "star": 4
  },
  {
    "content": "",
    "name": "徐君弼",
    "setTime": "3 年前",
    "star": 3
  },
  {
    "content": "旁邊有電動機車充電站",
    "name": "Bill Wang",
    "setTime": "3 年前",
    "star": 4
  },
  {
    "content": "",
    "name": "江節美",
    "setTime": "3 年前",
    "star": 5
  },
  {
    "content": "",
    "name": "王勝泰",
    "setTime": "3 年前",
    "star": 3
  },
  {
    "content": "唉！本人10月10ㄖ特地過來發現落葉一堆，應該是沒人很久了。花蓮有好幾個點再訪時都變荒廢",
    "name": "阪京伊集院",
    "setTime": "3 年前",
    "star": 1
  },
  {
    "content": "",
    "name": "linjan Huang",
    "setTime": "3 年前",
    "star": 2
  },
  {
    "content": "",
    "name": "lunhua liu",
    "setTime": "3 年前",
    "star": 4
  },
  {
    "content": "",
    "name": "Arena Pan",
    "setTime": "3 年前",
    "star": 4
  },
  {
    "content": "去了兩次都不是休館時間，但是都沒開...",
    "name": "Dory",
    "setTime": "3 年前",
    "star": 1
  },
  {
    "content": "",
    "name": "陳育廉",
    "setTime": "3 年前",
    "star": 5
  },
  {
    "content": "",
    "name": "慈玟狼嚎",
    "setTime": "4 年前",
    "star": 4
  },
  {
    "content": "",
    "name": "杜建華",
    "setTime": "4 年前",
    "star": 2
  },
  {
    "content": "跑馬拉松經過，下雨沒特別進去",
    "name": "李彥廣",
    "setTime": "4 年前",
    "star": 3
  },
  {
    "content": "沒有開放喔!7/9（二）早上",
    "name": "邱莉惠",
    "setTime": "4 年前",
    "star": 1
  },
  {
    "content": "",
    "name": "BOBEE LU",
    "setTime": "4 年前",
    "star": 5
  },
  {
    "content": "",
    "name": "温永盛",
    "setTime": "4 年前",
    "star": 5
  },
  {
    "content": "",
    "name": "羽小希",
    "setTime": "4 年前",
    "star": 5
  },
  {
    "content": "典雅的舊房子，有小園圃和高高斜斜的屋頂，氛圍適合做50人左右的藝文活動運用\n將音樂家的故居完整保留，提供懷念與懷想的空間！\n令人懷念的老房子 有著許多花蓮人的回憶~\n美麗的老房子、熱心的鄭執行長為我們介紹，也可以好好了解「洄瀾音樂之父」郭老師的故事\n木造日式老建築，隱藏在j巷弄之中，給人一種幽靜的感覺，場內可以舉辦靜態活動，別有一番風味。\n用古色古香歷史建築 紀念洄瀾音樂之父 用音樂連繫洄瀾的記憶與生命 而洄瀾音樂之父 凝聚了花蓮人的共同記憶。 這是一處建築 音樂 大師與歷史 藝術 人文融合的好所在。",
    "name": "林楹棟",
    "setTime": "4 年前",
    "star": 4
  },
  {
    "content": "",
    "name": "黃國瑞",
    "setTime": "4 年前",
    "star": 4
  },
  {
    "content": "",
    "name": "蔡志宏",
    "setTime": "4 年前",
    "star": 4
  },
  {
    "content": "",
    "name": "Boshen Huang",
    "setTime": "4 年前",
    "star": 4
  },
  {
    "content": "",
    "name": "Wencheng Lin",
    "setTime": "4 年前",
    "star": 5
  },
  {
    "content": "歷史啊",
    "name": "Poetics Chen (Poetics)",
    "setTime": "4 年前",
    "star": 5
  },
  {
    "content": "",
    "name": "林焜堯",
    "setTime": "4 年前",
    "star": 5
  },
  {
    "content": "將音樂家的故居完整保留，提供懷念與懷想的空間！",
    "name": "傅廷暐",
    "setTime": "4 年前",
    "star": 5
  },
  {
    "content": "",
    "name": "陳淑甄",
    "setTime": "4 年前",
    "star": 4
  },
  {
    "content": "",
    "name": "鄧小豪",
    "setTime": "4 年前",
    "star": 3
  },
  {
    "content": "古色古香，文物保存很好",
    "name": "Hansheng Hsu",
    "setTime": "4 年前",
    "star": 5
  }
]