[
  {
    "content": "",
    "name": "邱富龍",
    "setTime": "42 分鐘前",
    "star": 5
  },
  {
    "content": "體驗大自然，享受芬多精，離市區很近，是個散心的好地方。",
    "name": "Turbo1 Koong",
    "setTime": "9 小時前",
    "star": 5
  },
  {
    "content": "感覺沒什麼整理 不太想繼續往上走",
    "name": "Wilson Wang",
    "setTime": "5 天前",
    "star": 1
  },
  {
    "content": "",
    "name": "許志遠",
    "setTime": "2 週前",
    "star": 5
  },
  {
    "content": "",
    "name": "張博翔",
    "setTime": "3 週前",
    "star": 5
  },
  {
    "content": "",
    "name": "盧光遠",
    "setTime": "4 週前",
    "star": 4
  },
  {
    "content": "",
    "name": "Hsinyao Yang",
    "setTime": "1 個月前",
    "star": 5
  },
  {
    "content": "讚",
    "name": "黃耀廷",
    "setTime": "2 個月前",
    "star": 5
  },
  {
    "content": "",
    "name": "Chihhung Hu",
    "setTime": "2 個月前",
    "star": 5
  },
  {
    "content": "如果不喜歡18尖山，太多人，想安靜的體驗大自然，建議可來和18尖山相鄰的高峰植物園。",
    "name": "呂秉翰",
    "setTime": "2 個月前",
    "star": 5
  },
  {
    "content": "免費入園，入口處有機車停車場，入口上方另有汽車停車場，安靜自然，人不多，地方不大，小爬一趟來回約40分鐘，很適合週末小健行",
    "name": "Trans Mob",
    "setTime": "2 個月前",
    "star": 5
  },
  {
    "content": "",
    "name": "MS Wu",
    "setTime": "2 個月前",
    "star": 3
  },
  {
    "content": "植物多樣 步道平緩",
    "name": "陳俊穎",
    "setTime": "2 個月前",
    "star": 5
  },
  {
    "content": "免費參觀，園區附近保有自然景觀的地方，有步道可以散步走完整圈約一個小時，但由於實在太貼近自然生態「蚊蟲」也超多……造訪前建議做好防蚊措施……",
    "name": "CHUCHU YI",
    "setTime": "2 個月前",
    "star": 4
  },
  {
    "content": "讚",
    "name": "Apollo Su",
    "setTime": "3 個月前",
    "star": 5
  },
  {
    "content": "",
    "name": "黃任豪",
    "setTime": "3 個月前",
    "star": 4
  },
  {
    "content": "",
    "name": "PAN Cheng-Yu潘正育",
    "setTime": "3 個月前",
    "star": 5
  },
  {
    "content": "",
    "name": "lahung Lu",
    "setTime": "3 個月前",
    "star": 4
  },
  {
    "content": "蚊蟲很多 去要注意",
    "name": "陳志鵬",
    "setTime": "3 個月前",
    "star": 4
  },
  {
    "content": "漂亮的森林非常平靜和新鮮的空氣很適合四處走走",
    "name": "Riza Cabrera",
    "setTime": "3 個月前",
    "star": 5
  },
  {
    "content": "蚊蟲有點多",
    "name": "pen em",
    "setTime": "3 個月前",
    "star": 2
  },
  {
    "content": "",
    "name": "Ali Kan",
    "setTime": "4 個月前",
    "star": 5
  },
  {
    "content": "這是當初日本做為林業試驗成立的樹木園之一\n另外嘉義和美濃的都很棒\n一入園的檸檬桉 白千層 樟樹 麵包樹 印度黃檀等都高聳如巨人",
    "name": "Shufang Chen",
    "setTime": "4 個月前",
    "star": 5
  },
  {
    "content": "樹木多，大太陽也不太會熱，缺點是廁所不乾淨。",
    "name": "林秋君",
    "setTime": "4 個月前",
    "star": 4
  },
  {
    "content": "",
    "name": "George Young",
    "setTime": "4 個月前",
    "star": 4
  },
  {
    "content": "",
    "name": "江國柱",
    "setTime": "4 個月前",
    "star": 4
  },
  {
    "content": "蚊子滿多,有喝的水可裝",
    "name": "Willis WEN",
    "setTime": "4 個月前",
    "star": 3
  },
  {
    "content": "植物相普通\n大多位於山坡地\n機具不易到達\n因此為半野放式的方式管理\n地被灌木層以九節木為優勢\n步道維護的還不錯\n只是有些「非典型步道」\n為當地人所踩踏出來\n但尚清晰易走\n即時假日前來\n遊人三三兩兩\n入口停汽機車方便\n制高點奉茶亭處有飲水機可以裝水\n這點倒是挺方便\n建議若雨天勿前往\n部份泥土路溼滑堆積落葉\n安全為主",
    "name": "Hsin昕",
    "setTime": "4 個月前",
    "star": 4
  },
  {
    "content": "離市區近又可以吸收芬多精的散步路線",
    "name": "alex Lee",
    "setTime": "4 個月前",
    "star": 4
  },
  {
    "content": "珍貴的奇花異木，步道上的珍貴樹種很多，健走的賀地方！",
    "name": "曾日法",
    "setTime": "5 個月前",
    "star": 4
  },
  {
    "content": "路邊備有汽車停車場，入園處則有機車停車位。\n\n免費入園。\n\n與其說是植物園更像是登山步道，山道修整的很好走，不陡平緩曬不到太陽....。\n\n#新竹市 #東區 #高峰植物園",
    "name": "過客",
    "setTime": "6 個月前",
    "star": 5
  },
  {
    "content": "",
    "name": "Sanders CH",
    "setTime": "6 個月前",
    "star": 5
  },
  {
    "content": "",
    "name": "pham thanh nha",
    "setTime": "6 個月前",
    "star": 5
  },
  {
    "content": "市中擬山區",
    "name": "王少凡04號",
    "setTime": "6 個月前",
    "star": 5
  },
  {
    "content": "",
    "name": "葉秀恆",
    "setTime": "6 個月前",
    "star": 5
  },
  {
    "content": "高峰植物園，新竹市區除十八尖山，戶外走走的好去處，園區步道好走，主要都是各種樹木，整個繞一圈大約1小時",
    "name": "Ryan Chen",
    "setTime": "6 個月前",
    "star": 4
  },
  {
    "content": "很幽靜的步道，路況良好易健行登高，走完一趟約一個半鐘頭。",
    "name": "魏啟華",
    "setTime": "6 個月前",
    "star": 4
  },
  {
    "content": "不錯的健走步道，多認識一些植物。",
    "name": "施順富",
    "setTime": "7 個月前",
    "star": 5
  },
  {
    "content": "2023/01/26（星期四）\n車停旁邊的停車場（免費），繞一圈大約1個小時。輕鬆！👍\n\n今天天氣這麼冷，螞蟻依然出來逛大街。😵‍💫",
    "name": "羅運興",
    "setTime": "7 個月前",
    "star": 4
  },
  {
    "content": "很不錯的地方。原始，没水泥地。可全家運動健行。",
    "name": "S.C HU",
    "setTime": "7 個月前",
    "star": 4
  },
  {
    "content": "園區裡面有許多高大型植樹（尤其是有一顆巨大的芒果🌲），迷霧竹林也分散多處，松鼠東竄西竄穿梭在林間，到處可見講解老師帶領著一群小朋友在解說問答，內容可謂琳瑯滿目。 …",
    "name": "溫Win知新chief",
    "setTime": "7 個月前",
    "star": 5
  },
  {
    "content": "",
    "name": "江盛文",
    "setTime": "7 個月前",
    "star": 3
  },
  {
    "content": "第二次到訪，人蠻少的，景觀不錯。",
    "name": "邱桂蓮",
    "setTime": "7 個月前",
    "star": 5
  },
  {
    "content": "♥️♥️♥️",
    "name": "bingo009hsu",
    "setTime": "7 個月前",
    "star": 5
  },
  {
    "content": "樹很大！",
    "name": "德輝何",
    "setTime": "7 個月前",
    "star": 3
  },
  {
    "content": "",
    "name": "黃宇",
    "setTime": "7 個月前",
    "star": 5
  },
  {
    "content": "市區旁的祕境",
    "name": "Alex Cheng",
    "setTime": "7 個月前",
    "star": 5
  },
  {
    "content": "有許多植物但都不認識",
    "name": "蔡易軒",
    "setTime": "7 個月前",
    "star": 5
  },
  {
    "content": "原始的樹林風貌",
    "name": "Wen Yun Tai",
    "setTime": "7 個月前",
    "star": 4
  },
  {
    "content": "打發時間的地方",
    "name": "劉智威",
    "setTime": "7 個月前",
    "star": 3
  },
  {
    "content": "很適合",
    "name": "Steven lu",
    "setTime": "7 個月前",
    "star": 5
  },
  {
    "content": "步道很好走，有鋪磚也有土路，沿途草木扶疏，天氣好，加上新竹的大風，風吹樹搖，很熱鬧啊！",
    "name": "Laura Pan",
    "setTime": "8 個月前",
    "star": 4
  },
  {
    "content": "",
    "name": "Jasper Huang",
    "setTime": "8 個月前",
    "star": 5
  },
  {
    "content": "🍒高峰植物園\n11月某個週一下午3點來訪\n無需門票、有機車停車格\n\n園區環境很好，下午的陽光非常舒適，大約一小時內就可以走完。但是蚊子真的非常多！請大家一定要擦防蚊液前往🙏\n\n步道有小石頭路、階梯、泥土路、木棧道等，但階梯和泥土路偏多，腿腳不好的老人家不適合前往～\n\n園區內叉路頗多，有很多走法，因此想休閒一點的人可以不用全部繞完。一個小時內是幾乎沒有停下來，繞最大圈的時間喔\n\n植物沒有特別介紹的感覺，種類上沒有看出什麼特別的，比起植物園感覺很像在爬山散步。",
    "name": "余采容",
    "setTime": "8 個月前",
    "star": 4
  },
  {
    "content": "它尚未向公眾開放..但有些人正在偷偷摸摸。這個地方安靜而令人毛骨悚然，但道路乾淨整潔，我不知道為什麼他們將其關閉",
    "name": "virna hung",
    "setTime": "8 個月前",
    "star": 4
  },
  {
    "content": "假日闔家大小好去處，環狀步道好走、階梯平緩、山不高，園區有許多老樹，除在地樟樹、相思樹、由加麗、芒果樹外也有其他少見樹木，例如麵包樹、南洋杉⋯⋯步道邊樹木有掛告示介紹樹名，園區友善貼心設施有地圖告示完善、廁所多、山頂熱水供應遊客可泡咖啡、泡茶等，也推薦毛小孩一起來也不錯。",
    "name": "大黑毛",
    "setTime": "8 個月前",
    "star": 4
  },
  {
    "content": "步道不長，高度落差也不大，但有一點年久失修，部份路段長青苔，會滑。",
    "name": "莊瑞朗",
    "setTime": "8 個月前",
    "star": 4
  },
  {
    "content": "",
    "name": "曾Carol",
    "setTime": "8 個月前",
    "star": 4
  },
  {
    "content": "風景很棒又美",
    "name": "林耕安",
    "setTime": "8 個月前",
    "star": 4
  },
  {
    "content": "適合散步的植物園區，種植各種植物可供觀賞了解。",
    "name": "林佳平",
    "setTime": "9 個月前",
    "star": 5
  },
  {
    "content": "螞蟻真的太多了，雖然步道走起來算舒服，但走了10分鐘後，真的找不到沒有螞蟻的地方，好不容易撐到了階梯，想說上面總該沒有螞蟻了吧，結果階梯上是更多的螞蟻，只好快點落跑。",
    "name": "Ken Chen",
    "setTime": "9 個月前",
    "star": 2
  },
  {
    "content": "新竹市還需改善的地方、落葉超多、無人清理、蚊蟻超多、已不太適合小孩子的環境、市政府請加油~",
    "name": "林瑞禎",
    "setTime": "10 個月前",
    "star": 3
  },
  {
    "content": "",
    "name": "Wy Tseng",
    "setTime": "10 個月前",
    "star": 3
  },
  {
    "content": "風景優美",
    "name": "洪禾明",
    "setTime": "10 個月前",
    "star": 5
  },
  {
    "content": "市區內的祕境，園區內植栽自然、沒有太多人工化，路線有輕微起伏又不會太長，園區除公廁外亦設有飲水機，相當值得稱讚。此地適合親子半日遊，亦可串聯青草湖作一日遊規劃。",
    "name": "游維倫",
    "setTime": "10 個月前",
    "star": 4
  },
  {
    "content": "優質植物園，比台北的自然不少。",
    "name": "張瀚文",
    "setTime": "10 個月前",
    "star": 5
  },
  {
    "content": "一進來就遇到斯豪文氏攀蜥（應該是？\n不過只走了下面短短的步道沒有繞上山一圈\n蚊蟲不少，忘了給女鵝帶防蚊液噴\n只好早早離去，下次再訪～\n\nPS:看到天橋下的正門入口後\n真正的停車場要再往後開一點\n不是很顯眼",
    "name": "Yongcheng Kao",
    "setTime": "10 個月前",
    "star": 4
  },
  {
    "content": "去新竹找兒子, 計畫約 1 到 1.5 天的時間, 所以就選擇 新竹近郊的 高峰植物園.\n\n這裡是免費參觀的植物園區, 你可以選擇你想要參觀的植物區(參考地圖, 園區規畫得很好), 也可以環繞整個園區一圈.  路面小徑很好走, 遇到彎路, 也都有指標.  植物總類不少, 算是輕鬆的踏青路線.\n\n只可惜蚊子多, 螞蟻也很多.  此外停車位不太多, 入園旁邊約只能停 10 多輛.  今天算運氣好, 剛好停到最後一個位置.  恐怖的是 要離開時, 發現螞蟻大軍 已經 爬了不少在 門邊, 後車箱蓋.",
    "name": "Sunny Shiao",
    "setTime": "11 個月前",
    "star": 3
  },
  {
    "content": "雖然蚊蟲很多，但大自然的環境還不錯！",
    "name": "CHE WEI HSU",
    "setTime": "11 個月前",
    "star": 5
  },
  {
    "content": "新竹白天的散步地點，晚上沒什麼燈，建議白天活動。",
    "name": "Alice Huang",
    "setTime": "11 個月前",
    "star": 5
  },
  {
    "content": "繞一圈大概一小時，老少咸宜，可是超多超多螞蟻喔！",
    "name": "Nancy Catcat",
    "setTime": "11 個月前",
    "star": 5
  },
  {
    "content": "220917\n好可惜高峰植物園腹地不小\n應該是個可以給孩子豐富的植物教育的地方才對\n整個植物園人煙稀少荒煙蔓草⋯⋯\n而且蚊子真的好多啊⋯⋯\n下午在植物園到處都看到滿滿的螞蟻🐜螞蟻🐜螞蟻🐜\n晚上發生地震了\n莫非是牠們感受到地震前兆的關係😱",
    "name": "李小梅",
    "setTime": "11 個月前",
    "star": 3
  },
  {
    "content": "",
    "name": "Chuang swirl",
    "setTime": "11 個月前",
    "star": 4
  },
  {
    "content": "登山步道有人在整理，廁所也算乾淨，整個園區保留原始風貌，不錯的小型踏青去處....\n只是    螞蟻，螞蟻，到處是螞蟻，密密麻麻的，絕對超乎想像\n怕螞蟻的慎入，\n喜歡研究螞蟻的，真的不會讓您失望",
    "name": "Pancat Pan",
    "setTime": "11 個月前",
    "star": 4
  },
  {
    "content": "",
    "name": "陳榮杰",
    "setTime": "11 個月前",
    "star": 5
  },
  {
    "content": "不錯的地方，但有蚊子",
    "name": "Y C",
    "setTime": "11 個月前",
    "star": 4
  },
  {
    "content": "",
    "name": "Jainder Ju",
    "setTime": "1 年前",
    "star": 3
  },
  {
    "content": "",
    "name": "秦祥益",
    "setTime": "1 年前",
    "star": 5
  },
  {
    "content": "環境清幽散步還不錯 但晚上可能有點黑",
    "name": "Ethan",
    "setTime": "1 年前",
    "star": 4
  },
  {
    "content": "林相還不錯唯美中不足的\n靠近馬路邊車流聲大",
    "name": "高文祥",
    "setTime": "1 年前",
    "star": 5
  },
  {
    "content": "樹多不曬\n蚊蟲螞蟻稍多",
    "name": "Henry Cho (彥宏)",
    "setTime": "1 年前",
    "star": 5
  },
  {
    "content": "",
    "name": "郁哲",
    "setTime": "1 年前",
    "star": 4
  },
  {
    "content": "雖說是植物園但植物種類乏善可陳...\n但設施該有的都有特別是有冰水開飲機，沿路都有詳盡路線指示牌\n做為淺山步道走起來平易近人但沒有什麼美景可言，植物歧異度低\n然後到處都是密密麻麻的螞蟻，蝴蝶、鳥類種類多\n將此地當作副景點逛逛走走即可，不需要特地走一趟",
    "name": "Hayata Chen",
    "setTime": "1 年前",
    "star": 2
  },
  {
    "content": "",
    "name": "Gomax Lo",
    "setTime": "1 年前",
    "star": 5
  },
  {
    "content": "",
    "name": "胡永德",
    "setTime": "1 年前",
    "star": 3
  },
  {
    "content": "安靜，不錯的地方。適合所有人。適合散步。",
    "name": "Po-Hsiang Wang",
    "setTime": "1 年前",
    "star": 5
  },
  {
    "content": "",
    "name": "陳大雄",
    "setTime": "1 年前",
    "star": 5
  },
  {
    "content": "離新竹市區很近的植物園，可以免費參觀，與免費的停車場。\n步道平坦規劃良好，最大的O型路線大約1小時可走完，可依自己體力與時間，選擇要走的路徑長短，有很多的叉路可以走回起點。\n步道內有廁所、飲水機，算是滿休閒的一條步道。\n步道常走在樹蔭底下，較不會被太陽直曬，在各個叉路口有明確的指標與導覽圖，不怕迷路，路邊的植物也會掛有解說牌，如果對各植物有興趣也可停下腳步看看。\n走完植物園，隔壁就是十八尖山，若有體力還想繼續走，可走到對面的桐花廣場，可接續到十八尖山的步道。",
    "name": "李冠霆",
    "setTime": "1 年前",
    "star": 5
  },
  {
    "content": "",
    "name": "Juaing Huang",
    "setTime": "1 年前",
    "star": 4
  },
  {
    "content": "",
    "name": "Jeff LO",
    "setTime": "1 年前",
    "star": 5
  },
  {
    "content": "天氣很熱",
    "name": "Roda Berputar",
    "setTime": "1 年前",
    "star": 5
  },
  {
    "content": "",
    "name": "藍永吉",
    "setTime": "1 年前",
    "star": 5
  },
  {
    "content": "適合慢活運動的好地方 滿滿的芬多精",
    "name": "Kelly Chiu",
    "setTime": "1 年前",
    "star": 4
  },
  {
    "content": "感覺被棄置沒有整理",
    "name": "38nieh Nieh",
    "setTime": "1 年前",
    "star": 1
  },
  {
    "content": "",
    "name": "yu-tang tai",
    "setTime": "1 年前",
    "star": 4
  },
  {
    "content": "免費停車場, 但琉璃蟻好多啊\n小心車被當蟻窩\n\nFree parking space,\nFull of Dolichoderus thoracicus, be aware that your car becomes its nest",
    "name": "Bing Ju",
    "setTime": "1 年前",
    "star": 5
  },
  {
    "content": "",
    "name": "小黑人",
    "setTime": "1 年前",
    "star": 5
  },
  {
    "content": "生態豐富多樣，有廁所、飲水機、停車場👍不適合推娃娃車，沿途有小段樓梯、泥地跟樹根，適合三歲以上步行穩定的親子，三代出遊散步的好選擇。 …",
    "name": "邱珮玉",
    "setTime": "1 年前",
    "star": 5
  },
  {
    "content": "很天然步道， 適合帶小孩來運動",
    "name": "patrick chu",
    "setTime": "1 年前",
    "star": 5
  },
  {
    "content": "都市中的森林密境",
    "name": "趙翔翔",
    "setTime": "1 年前",
    "star": 4
  },
  {
    "content": "很喜歡這個新竹市內的原始植物園，還有部分的原始步道，景觀視覺良好，適合森呼吸有益身心。",
    "name": "Charles Tan",
    "setTime": "1 年前",
    "star": 4
  },
  {
    "content": "蚊子很多，小心長長滑溜溜的動物",
    "name": "Lance Tsai",
    "setTime": "1 年前",
    "star": 4
  },
  {
    "content": "",
    "name": "Mark W",
    "setTime": "1 年前",
    "star": 4
  },
  {
    "content": "",
    "name": "Huan-Wen Chen",
    "setTime": "1 年前",
    "star": 4
  },
  {
    "content": "同樣一個景點\n在不同人眼中會有不一樣的風景\n。\n剛入園區時看到一棵大樹🌳\n看到一個爸爸帶著小孩在樹旁東張西望\n手裡還拿著一個桶子🪣\n原來他們在觀察昆蟲\n整個植物園就是他們的教科書\n。\n走一會兒\n又看到一名拿著相機的人📸\n像看到寶藏般對著樹叢拍呀拍\n。\n對我來說像是輕鬆的健行步道\n想要散步看看植物🌲、樹木🪵、花朵💐\n但又不想跑太遠的時候可以來的地方\n。\n剛好遇上桐花季時🌸\n可以看到桐花落在地上\n白白的桐花也是很舒壓\n。\n園區蚊子蠻多的🦟\n怕被叮的話記得噴防蚊液🐜",
    "name": "Vicky Li",
    "setTime": "1 年前",
    "star": 5
  },
  {
    "content": "環境乾淨，在園區旁邊有一個散步的地方很不錯，裡面還設有垃圾桶。",
    "name": "William Weng",
    "setTime": "1 年前",
    "star": 5
  },
  {
    "content": "散步，休閒，親子活動皆可",
    "name": "杜雲禎",
    "setTime": "1 年前",
    "star": 3
  },
  {
    "content": "免費參觀的植物園，有點像是郊山原始森林，植物茂密只有少數登山運動的民眾，算是很舒服的步道。寶山路大門外面有免費汽車停車場(有15個停車位)，大門進來後有免費機車停車場。園區遇到岔路就會有導覽解說圖，不用擔心迷路。植物解說教室和溫室旁邊有廁所，奉茶亭有飲水機，繞一圈大約一小時。之前琉璃蟻(一種螞蟻)超多，現在有在做防治已經少很多。蚊子有點多，記得做好防蚊。考量自然生態環境，晚上不開燈，建議入園時間8:00~17:00。大門旁邊有「桐花天空之橋」，可以走到馬路對面的「十八尖山桐花廣場」，廣場有廁所飲水機，後面有步道可以走到十八尖山。",
    "name": "陳必榮",
    "setTime": "1 年前",
    "star": 5
  },
  {
    "content": "顛覆您對植物園的觀感！",
    "name": "マジニ（majini）",
    "setTime": "1 年前",
    "star": 5
  },
  {
    "content": "裡頭比想像中大很多",
    "name": "Ian Chou",
    "setTime": "1 年前",
    "star": 5
  },
  {
    "content": "舒服、悠閒、適合假日運動踏青。",
    "name": "Jerry家瑞",
    "setTime": "1 年前",
    "star": 5
  },
  {
    "content": "整潔、人少、空氣好！\n螞蟻很多。",
    "name": "Winnie Q Ni",
    "setTime": "1 年前",
    "star": 5
  },
  {
    "content": "",
    "name": "曾國宏",
    "setTime": "1 年前",
    "star": 3
  },
  {
    "content": "鄰近新竹市區的清幽步道",
    "name": "Michael Wang",
    "setTime": "1 年前",
    "star": 4
  },
  {
    "content": "",
    "name": "Nicholas Lin",
    "setTime": "1 年前",
    "star": 5
  },
  {
    "content": "園內維護很ok，也保留了森林的景觀，步道好走，中途還有賀眾牌飲水機。",
    "name": "Anchovy Frappe",
    "setTime": "1 年前",
    "star": 5
  },
  {
    "content": "不收費的植物園",
    "name": "Hairay Lin",
    "setTime": "1 年前",
    "star": 5
  },
  {
    "content": "免費，好風景，植物種類豐富，全程走在樹蔭下，運動、散步、生態、休閒好地方的，可與十八尖山串接，一次兩享受。\n\n最大問題是：琉璃蟻！太多了，到處都是，千萬要小心，扶手、椅子、樹根、地面，到處都是，成千上億隻，不能用手扶、不可隨便坐！就是要大家不能停一直走，真的是活動的好地方！暈😵‍💫⋯⋯",
    "name": "李好命",
    "setTime": "1 年前",
    "star": 5
  },
  {
    "content": "很原始的植物園，園內步路很好走，本來應該是一個很好的休閒地點，不過整個園區到處都是琉璃蟻，在同一位置久停可能就會有螞蟻上身，因為琉璃蟻就像遊牧民族，適應力很強，且為多蟻后，傳播力很強，上車前最好檢查一下，不小心把蟻后帶回家，就可能養了一窩的螞蟻。",
    "name": "Jeffery Chang",
    "setTime": "1 年前",
    "star": 3
  },
  {
    "content": "逛一圈5分鐘 , 一堆路邊隨處可見的樹 , 還有一棟鬼屋 , 不要來浪費時間",
    "name": "amber wang (Anh Kuan)",
    "setTime": "1 年前",
    "star": 1
  },
  {
    "content": "不像植物園，比較像是都會郊區的小山。需要一點點腿力，想帶年幼子女同來的父母，慎入啊~",
    "name": "cherryjou",
    "setTime": "1 年前",
    "star": 4
  },
  {
    "content": "天氣好的時候滿好走的，輕鬆散步",
    "name": "張言浦",
    "setTime": "1 年前",
    "star": 5
  },
  {
    "content": "",
    "name": "志成鄒",
    "setTime": "1 年前",
    "star": 4
  },
  {
    "content": "",
    "name": "HL Lin",
    "setTime": "1 年前",
    "star": 5
  },
  {
    "content": "",
    "name": "Jessica Huang",
    "setTime": "1 年前",
    "star": 5
  },
  {
    "content": "",
    "name": "境芳",
    "setTime": "1 年前",
    "star": 4
  },
  {
    "content": "這裡有廁所、飲水機\n還有植物解說牌\n但感覺無人管理\n好幾棵樹都快死了\n⁡\n💰 免費入園\n📍 300新竹市東區寶山路 #高峰植物園\n⏰ 07:00-17:00（繞大O大概一小時）\n📅 五月有桐花季\n🚗 寶山路這側有免費停車場\n🎁 2022/2/17 前報名健行筆記「南山神壽任務」，走指定步道抽萬元Garmin手錶。\n⁡🔥更多分享請追蹤IG：cclemonyayaya，或FB搜尋「旅行計畫通」",
    "name": "寶石蕃薯",
    "setTime": "1 年前",
    "star": 4
  },
  {
    "content": "可以看到不常見的植物種，可面積太小了",
    "name": "盧莫非",
    "setTime": "1 年前",
    "star": 3
  },
  {
    "content": "",
    "name": "Neil Lin",
    "setTime": "1 年前",
    "star": 3
  },
  {
    "content": "悠閒",
    "name": "Ming Chi Wong",
    "setTime": "1 年前",
    "star": 5
  },
  {
    "content": "",
    "name": "顏秀如",
    "setTime": "1 年前",
    "star": 5
  },
  {
    "content": "",
    "name": "tingjie0707",
    "setTime": "1 年前",
    "star": 2
  },
  {
    "content": "",
    "name": "Jennifer Yu",
    "setTime": "1 年前",
    "star": 4
  },
  {
    "content": "",
    "name": "功夫關不住",
    "setTime": "1 年前",
    "star": 3
  },
  {
    "content": "",
    "name": "蕭嘉慧",
    "setTime": "1 年前",
    "star": 5
  },
  {
    "content": "",
    "name": "鍾玲",
    "setTime": "1 年前",
    "star": 1
  },
  {
    "content": "20201018 想想在新竹十多年來可能只來過兩三次, 但這次來卻讓我重新的定義了這個地方, 現在的我是滿喜歡這裡的. 跟旁邊的十八尖山相比, 這裡較小, 但人少且景色與步道更質樸, 想尋找緩步林間, 放空心靈的感覺, 你必須來這裡, 這樣的感覺是十八尖山無法給你的. 環狀步道繞行一圈要一個半小時. 它有兩個入口, 寶山路這邊的入口有大約 15 個汽車停車位, 高峰路的沒有車格要停路邊要碰運氣. 真的想走一大圈的話, 我推薦把車停在寶山路這邊, 入園之後往高翠路的入口走, 出園走去吃重慶孫子文牛肉麵, 加麵, 免費豆漿紅茶推飽飽, 然後再入園往寶山路入口走, 出園後走天橋接十八尖山繞行一圈再回寶山路牽車. 這樣就很大一圈囉. 園內是不太有在整理的, 廁所跟設施都已老舊, 植物也是放生款, 整潔度尚可 !",
    "name": "Awei13131313",
    "setTime": "1 年前",
    "star": 4
  },
  {
    "content": "散步好去處，人不多。",
    "name": "黃Tzu_淳",
    "setTime": "1 年前",
    "star": 4
  },
  {
    "content": "種類繁多，都市綠化先峰",
    "name": "楊全全",
    "setTime": "1 年前",
    "star": 5
  },
  {
    "content": "停車位有點少",
    "name": "范揚貢",
    "setTime": "1 年前",
    "star": 3
  },
  {
    "content": "美",
    "name": "洪忠義",
    "setTime": "1 年前",
    "star": 5
  },
  {
    "content": "一個植物園區，逛完整圈不用多久。",
    "name": "Jason Young",
    "setTime": "1 年前",
    "star": 3
  },
  {
    "content": "健行步道",
    "name": "陳彥臻",
    "setTime": "1 年前",
    "star": 5
  },
  {
    "content": "",
    "name": "林季宏",
    "setTime": "1 年前",
    "star": 4
  },
  {
    "content": "蚊子多 長袖長褲必備",
    "name": "洪士評",
    "setTime": "1 年前",
    "star": 4
  },
  {
    "content": "缺水、蚊子、疣胸琉璃蟻多導致物種多樣性減少",
    "name": "Rebecca",
    "setTime": "1 年前",
    "star": 5
  },
  {
    "content": "完全開放式無人管理，步道簡單平易近人，溫室已成廢墟哈哈哈哈",
    "name": "z Lu",
    "setTime": "1 年前",
    "star": 4
  },
  {
    "content": "一個還保持著很原始的山林小型植物園，即使是假日會來植物園走走的人並不會很多，園內步道還算是老幼咸宜的好走，植物園門口右邊沿著高峰路約2.30公尺的地方有小型車停車場，進入園內走到了最裡面，就有一個上坡階梯的步道，走上去後，有往左右兩邊的岔路口，在岔路口有園區的路線跟植物分佈地圖，依著地圖可以繞著園區遊覧，此園區內的樹林茂密，景觀原始，小蚊子多到繞著你隨時找機會要吸血，最好是穿著長袖的衣物跟先噴好防蚊液來防蚊叮咬，園內步道經過的地方，常常會看見存在已經年久的墳墓，整個園區感覺頗為陰森，忌諱這些的人不建議入園。\n如果是去十八尖山健走，中途有一岔路指標也可以走到這處高峰植物園來。",
    "name": "Kun John",
    "setTime": "1 年前",
    "star": 2
  },
  {
    "content": "",
    "name": "F Gg",
    "setTime": "1 年前",
    "star": 3
  },
  {
    "content": "非常棒 休閒運動的好去處\n部分的地上 螞蟻很多",
    "name": "陳佑佑",
    "setTime": "1 年前",
    "star": 5
  },
  {
    "content": "",
    "name": "I T",
    "setTime": "1 年前",
    "star": 3
  },
  {
    "content": "",
    "name": "Chen I Lai",
    "setTime": "1 年前",
    "star": 5
  },
  {
    "content": "非常舒適的運動步道，環境維護的很好，要前往運動時一定要帶防蚊液，蚊子螞蟻超多，推啊！比十八尖山讚！",
    "name": "馮素素",
    "setTime": "1 年前",
    "star": 5
  },
  {
    "content": "蚊子多，記得要帶防蚊液，對於小孩可能會有點難走，但整體上還算不錯👍 …",
    "name": "哲嘉吳（喳喳）",
    "setTime": "1 年前",
    "star": 5
  },
  {
    "content": "",
    "name": "何秀美",
    "setTime": "1 年前",
    "star": 5
  },
  {
    "content": "輕鬆的步道體驗",
    "name": "潘信安",
    "setTime": "1 年前",
    "star": 5
  },
  {
    "content": "",
    "name": "Johanny",
    "setTime": "1 年前",
    "star": 4
  },
  {
    "content": "普通，就是一個可以散步的郊山。",
    "name": "Jason Lee",
    "setTime": "1 年前",
    "star": 3
  },
  {
    "content": "可以從這繞到十八尖山\n比較少人來這走\n喜歡安靜的感覺👍 …",
    "name": "Chang, 小V (Vega)",
    "setTime": "1 年前",
    "star": 5
  },
  {
    "content": "是自然又好走的步道。慢慢走一圈差不多40分鐘，拍照取景也不錯。",
    "name": "Fang Maggie",
    "setTime": "1 年前",
    "star": 5
  },
  {
    "content": "步道沒在維護  走起來有點恐怖  可惜了",
    "name": "David H",
    "setTime": "1 年前",
    "star": 2
  },
  {
    "content": "",
    "name": "巧伶張",
    "setTime": "1 年前",
    "star": 4
  },
  {
    "content": "還不錯",
    "name": "鍾孝義",
    "setTime": "1 年前",
    "star": 3
  },
  {
    "content": "裡面沒什麼人，而且臨馬路會有車聲。\n對比還是十八尖山比較好。",
    "name": "林昭吟（小烏龜）",
    "setTime": "1 年前",
    "star": 3
  },
  {
    "content": "小而美, 疫情期間來走走還不錯。",
    "name": "Sara Bellavita",
    "setTime": "1 年前",
    "star": 4
  },
  {
    "content": "當做公園步道走走就不會失望了",
    "name": "albert c. wang",
    "setTime": "1 年前",
    "star": 3
  },
  {
    "content": "",
    "name": "蔡桂燈",
    "setTime": "1 年前",
    "star": 3
  },
  {
    "content": "在清華大學附近\n很清幽的植物園，慢慢走一小時內即可走完\n一路上只有遇到三個人是個適合放空的地方\n裡面蚊蟲不少，建議噴點防蚊液再進入\n奉茶庭是個可愛的小地方\n有飲水機能裝水非常貼心",
    "name": "Kelly Huang",
    "setTime": "1 年前",
    "star": 4
  },
  {
    "content": "很簡易的植物園，很多都封閉起來無法爬山上去，不過這有百年歷史就這樣放生式管理有點可惜！",
    "name": "尋路犬",
    "setTime": "1 年前",
    "star": 3
  },
  {
    "content": "",
    "name": "江jack",
    "setTime": "2 年前",
    "star": 4
  },
  {
    "content": "",
    "name": "王淳駿",
    "setTime": "2 年前",
    "star": 3
  },
  {
    "content": "",
    "name": "李彥廷",
    "setTime": "2 年前",
    "star": 4
  },
  {
    "content": "蚊子太多😑 …",
    "name": "Shih-Jie Lin",
    "setTime": "2 年前",
    "star": 3
  },
  {
    "content": "散步好地方，但小黑蚊很多要注意被叮，",
    "name": "傅學沛",
    "setTime": "2 年前",
    "star": 4
  },
  {
    "content": "",
    "name": "黃秀崇",
    "setTime": "2 年前",
    "star": 4
  },
  {
    "content": "",
    "name": "Sophie",
    "setTime": "2 年前",
    "star": 3
  },
  {
    "content": "城市中的綠洲",
    "name": "蘇炳和",
    "setTime": "2 年前",
    "star": 5
  },
  {
    "content": "",
    "name": "陳嘉輝",
    "setTime": "2 年前",
    "star": 5
  },
  {
    "content": "",
    "name": "Pierce Chen",
    "setTime": "2 年前",
    "star": 5
  },
  {
    "content": "場地較少整理好，沒鋪柏油路面，帶小孩去要噴很多防蚊液，優點是人超少，小孩抓到了3隻獨角仙，3隻螳螂，3隻蜥蜴，1隻4腳蛇，一堆蚱蜢，下雨天或剛下完雨千萬不要去，那路會很危險的",
    "name": "周彥甫",
    "setTime": "2 年前",
    "star": 5
  },
  {
    "content": "",
    "name": "CC Chang",
    "setTime": "2 年前",
    "star": 5
  },
  {
    "content": "",
    "name": "柯淩萍",
    "setTime": "2 年前",
    "star": 5
  },
  {
    "content": "",
    "name": "Roger Chao",
    "setTime": "2 年前",
    "star": 5
  },
  {
    "content": "享受大自然環境",
    "name": "宥驊",
    "setTime": "2 年前",
    "star": 5
  },
  {
    "content": "市區的一條越野山徑，因為不高所以沒有景色可以看，不過距離不長人潮不多，很適合越野跑步。",
    "name": "LiangJhen CHEN",
    "setTime": "2 年前",
    "star": 4
  },
  {
    "content": "",
    "name": "朱淑慧",
    "setTime": "2 年前",
    "star": 4
  },
  {
    "content": "",
    "name": "管進昌",
    "setTime": "2 年前",
    "star": 2
  },
  {
    "content": "",
    "name": "張賜勇",
    "setTime": "2 年前",
    "star": 5
  },
  {
    "content": "",
    "name": "陰森森新蚊",
    "setTime": "2 年前",
    "star": 5
  },
  {
    "content": "環境優美適合踏青",
    "name": "Jason Dad",
    "setTime": "2 年前",
    "star": 5
  }
]